[
  {
    "id": "1519551258008326145",
    "lang": "in",
    "text": "Kembali Posting Instagram, Potret Nia Ramadhani Liburan di Disneyland Bareng Ardi Bakrie &amp; Anak-Anaknya: Kini Punya Rambut Ungu! https://t.co/1MEMPf40AR"
  },
  {
    "id": "1519551257114931201",
    "lang": "in",
    "text": "Indonesia’s Bukalapak records Q1 profit after Allo Bank investment https://t.co/gJcsr9KvEu"
  },
  {
    "id": "1519551255147737088",
    "lang": "in",
    "text": "RT @Lilcomons: Menteri BUMN @erickthohir menghadiri acara \nInaugural Flight Ceremony Jakarta To Bali, Pelita Air.\n\nSemoga Pelita Air bisa m…"
  },
  {
    "id": "1519551249200295936",
    "lang": "in",
    "text": "6 Tradisi Makan Bersama Saat Lebaran Khas Daerah Indonesia https://t.co/0KqpJgKZp1"
  },
  {
    "id": "1519551248147525632",
    "lang": "in",
    "text": "@hyang_wisnu @kemkominfo @PlateJohnny Mewujudkan pemerataan pembangunan di wilayah Barat dan Timur Indonesia lewat pembangunan IKN.\n@kemkominfo @PlateJohnny"
  },
  {
    "id": "1519551245081788417",
    "lang": "in",
    "text": "RT @Ebitlew_: Syukur pada Allah kami hadiahkan 1 lori minyak masak 1.38 Tan. 115kotak. 1380paket untuk orang Kronjo Balarajabarat Banten In…"
  },
  {
    "id": "1519551243680911361",
    "lang": "in",
    "text": "RT @Human_B: Malaysia Cabut peraturan Pandemi dan ga pakai scan² lagi.... nah negara Indonesia kok ga bisa?\n@KemenkesRI dan @PBIDI \n\n@VFath…"
  },
  {
    "id": "1519551243609591814",
    "lang": "in",
    "text": "Sigit Ardian akhirnya dipanggil masuk ke timnas voli putra Indonesia yang akan berlaga ke SEA Games 2021. #TImnasVoliPutraIndonesia https://t.co/Bg1X2moi0F"
  },
  {
    "id": "1519551242527449094",
    "lang": "in",
    "text": "bukti klo sesama muslim itu bersaudara,, tpi muslim yg taqwa ya bukan munafik kek kebanyakan di indonesia dri ormas yg suka radika radikul bubarin pengajian umat muslim.. https://t.co/TEgQmUmUFx"
  },
  {
    "id": "1519551234507608064",
    "lang": "in",
    "text": "RT @DiposuroP: Dear : PKI ( Perkumpulan Kadrun Indonesia ) \n\nCoba kalian bilang ini semua para oknum drun..😂😂 https://t.co/0yFsGycQYC"
  },
  {
    "id": "1519551232200916992",
    "lang": "in",
    "text": "Jonatan Christie menjaga asa tunggal putra Indonesia dengan lolos perempatfinal Badminton Asia Championship 2022. 👏\n\nLain kesempatan, The Daddies malah tumbang. 😔\n\n#BAC2022  https://t.co/vO5ffKfDXk"
  },
  {
    "id": "1519551222268960769",
    "lang": "in",
    "text": "Mending lu beli kopi liong dah buru, biar semua indonesia tau kopi sachet terenak dimuka bumi https://t.co/XJUsCRAxyi"
  },
  {
    "id": "1519551209304064000",
    "lang": "in",
    "text": "RT @RadarSosmed1: 1. Puluhan anak muda di Kota Palembang yg tergabung di Komunitas Ngopi Wong Kito (KN-WK) mendeklarasikan Dukungan kepada…"
  },
  {
    "id": "1519551196411068416",
    "lang": "in",
    "text": "RT @sigitwid: Apakah Pak @aniesbaswedan tahu soal kaos ini?\n\nMudik gratis ini menggunakan dana APBD DKI Jakarta sebesar Rp 13,7 miliar, kal…"
  },
  {
    "id": "1519551190769737728",
    "lang": "in",
    "text": "Alhamdulillah Alloh &amp; Surat Al Mu’minun Selalu Bersholawat Untuk Nabi Muhammad\n.\n❤️ WhatsApp https://t.co/Nq6RbFRXU1\n🌏 Web https://t.co/vxqLFAjAfK\n.\nIkuti @blogrosululloh di 👇\nFacebook Twitter Instagram Linkedin VK Pinterest Reddit Tumblr\n.\n#islam #indonesia #sholawat #Muhammad https://t.co/xW68pFSTpi"
  },
  {
    "id": "1519551188768722944",
    "lang": "in",
    "text": "Dalam penyambutan pertemuan budaya G20, Partai Rakyat Adil Makmur (Prima) meminta agar pemerintah Indonesia berbicara soal ketidakadilan demi menjaga kebahagiaan bersama. \n\n#PRIMA #PartaiPRIMA #PartaiRakyatBiasa \n\nBaca selengkapnya:\nhttps://t.co/WxPSZM85wP"
  },
  {
    "id": "1519551177867681792",
    "lang": "in",
    "text": "RT @karman_mustamin: Buat adik2 mahasiswa yg bilang kesejahteraan tdk didapatkan di era Jokowi, selamat mudik ke kampung halaman lewat jala…"
  },
  {
    "id": "1519551173920837633",
    "lang": "in",
    "text": "RT @dianasayangku: Di twitter kita boleh flexing dengan kriteria gaji 2-3 digit. Tapi di dunia nyata, banyak pegawai toko, penjaga counter,…"
  },
  {
    "id": "1519551172264480770",
    "lang": "in",
    "text": "RT @MALAYSIAVIRALL: Jemm kat Indonesia sebab orang balik nak beraya kat kampung. Dulu  Pernah ada kes ada orang mati sebab 2 hari terkandas…"
  },
  {
    "id": "1519551168619622400",
    "lang": "in",
    "text": "RT @Himan67392484: Cukup jakarta aja yang rusak 🤭🤭🤭🤭\nIndonesia jangan 🤣🤣🤣🤣"
  },
  {
    "id": "1519551154275127296",
    "lang": "in",
    "text": "Kegiatan dihadiri oleh Angkasa Pura I, Divisi Keimigrasian Kanwil Kemenkumham DIY, Kantor Imigrasi Kelas I TPI Yogyakarta, PT Lion Mentari Airlines, General Manager PT Garuda Indonesia (Persero) Tbk, PT Indonesia Air Asia, dan KKP Yogyakarta.\n\nKanwil Kemenkumham DIY Imam Jauhari"
  },
  {
    "id": "1519551154157359105",
    "lang": "in",
    "text": "🎁Apa saja sih yang akan kamu dapatkan dari webinar spesial Teknik Kimia ini?\n-E-certificate (insert nama peserta) dan Relasi\n-Materi Seminar\n-Rekaman Seminar\n-Doorprize (Discount Voucher Training Teknik Kuliah Indonesia)"
  },
  {
    "id": "1519551152899067909",
    "lang": "in",
    "text": "#BeriTebengan Indonesia - Indonesia, 28/04 23:00, 6 seat, Rp. 200.000, meeting point yang telah d... https://t.co/zJWuA4x2TJ @nebengers https://t.co/tEAIfHyHjW"
  },
  {
    "id": "1519551149627809792",
    "lang": "in",
    "text": "Apakah kamu sudah tahu rumor terkini dari sepakbola Indonesia? 🧐\n\nYuk simak selengkapnya disini... https://t.co/qUMf7eUWI0\n\nJangan lupa untuk berkomentar di setiap rumor panas yang ada di dalamnya! 🔥 https://t.co/ykNETGhvcU"
  },
  {
    "id": "1519551136042127361",
    "lang": "in",
    "text": "“Indonesia bisa diberi kuota tambahan dari sisa kuota haji negara lain yang tidak terserap,” –Puan Maharani https://t.co/WKiMGU4WIz"
  },
  {
    "id": "1519551134901612544",
    "lang": "in",
    "text": "RT @bayuarisandee: Putri KW mengalahkan WS 2 Korea\n\nStephanie Widjaja mengajak rubber An Seyong\n\nKomang Ayu mengajak rubber dan ketat di se…"
  },
  {
    "id": "1519551130887282689",
    "lang": "in",
    "text": "Selamat Siangg 🤗 Open Joki Tugas Dan Ulangan Realtime Matematika, Kimia, Bahasa Inggris, Bahasa Indonesia, Bahasa Jepang ✨\n\n📲 Minat? https://t.co/HChuTpY3ML"
  },
  {
    "id": "1519551123870613504",
    "lang": "in",
    "text": "Bahlil sdh pernah merasakan susah nya proses pengajuan izin investasi di Indonesia, mk nya disaat dia menjabat sbg pemangku pemberian izin dia tdk mau Pengusaha saat ini mengalami hal yg sama Spt yg pernah dia rasakan.. TOP Bahlil https://t.co/ZaoI0V2DxL"
  },
  {
    "id": "1519551115729154049",
    "lang": "in",
    "text": "RT @jstcforemployee: cerita tentang salah satu perusahaan televisi yang dimiliki oleh konglomerat indonesia berlogo warna merah."
  },
  {
    "id": "1519551114508599297",
    "lang": "in",
    "text": "RT @davidyao74: @triajaaa Nahhh... Makanya masyarakat Indonesia harus cerdas, jangan takut di intimidasi harus memilih si anies goblok. Jug…"
  },
  {
    "id": "1519551114202738688",
    "lang": "in",
    "text": "@detikcom Selamat atas terbentuknya PDSI. Smoga ekosistem kesehatan Indonesia jadi lebih baik dgn menjunjung tinggi profesionalitas dan nilai kemanusiaan. Jika sy butuh dokter, sy akan pilih dokter2 dr PDSI aja."
  },
  {
    "id": "1519551114114641920",
    "lang": "in",
    "text": "RT @yoongi4ddicted: @BTS_twt GOALS GLOBAL DAN INDONESIA!~\n\npre-made playlist: https://t.co/HkX4nQ29mp\n\nbesok waktu lagunya rilis, langsung…"
  },
  {
    "id": "1519551108665909248",
    "lang": "in",
    "text": "“Pemerintah harus bergerak cepat untuk memaksimalkan diplomasi agar Indonesia bisa mendapatkan kuota maksimal,”  --Puan Maharani https://t.co/UaZH2CQ0wt"
  },
  {
    "id": "1519551108037120001",
    "lang": "in",
    "text": "RT @tirta_cipeng: Jika kapasitas dokter di Ukur dari testimoni, apa bedanya dengan \"klinik tong fung fang feng\"\n\njangan heran banyak  dokte…"
  },
  {
    "id": "1519551102915854337",
    "lang": "in",
    "text": "RT @korantempo: Pembentukan Partai Mahasiswa Indonesia (PMI) dianggap sebagai upaya menggembosi gerakan mahasiswa. Ketua Umum PMI justru me…"
  },
  {
    "id": "1519551099195166722",
    "lang": "in",
    "text": "RT @Cantika82104633: Ada yg aneh kah dari ke 2 foto tsb?\nYg aneh justru mereka2 yg ribut, krn mereka iri Indonesia di terima oleh Elon Musk…"
  },
  {
    "id": "1519551097660002304",
    "lang": "in",
    "text": "RT @HopeOrangutan: 🥺🥺 EKSPLOITASI SATWA LIAR SIH INI. YUK BISA YUK NETIZEN INDONESIA LEBIH SELEKTIF DAN CERDAS LAGI BEDAIN TERKAIT INFLUENC…"
  },
  {
    "id": "1519551085907628032",
    "lang": "in",
    "text": "Selamat Siangg 💁🏻 Open Joki Tugas Dan Ulangan Realtime Matematika, Kimia, Bahasa Inggris, Bahasa Indonesia, Bahasa Jepang 📝\n\n📱 Minat? https://t.co/HChuTpY3ML"
  },
  {
    "id": "1519551083051646977",
    "lang": "in",
    "text": "Hajat Akbar G20 Lokomotif Kebangkitan Pariwisata Tanah Air https://t.co/Fiy6IAy9EI"
  },
  {
    "id": "1519551072825532416",
    "lang": "in",
    "text": "Ketua DPR RI Puan Maharani meminta pemerintah berupaya optimal melobi Arab Saudi agar Indonesia mendapat jatah kuota haji secara optimal. https://t.co/40WVPY6SFV"
  },
  {
    "id": "1519551065825243136",
    "lang": "in",
    "text": "RT @KemenkesRI: Update Cakupan Vaksinasi COVID-19 di Indonesia (27/4)\n \n#ayovaksin \n#SayaPilihSehat https://t.co/HFgTyY19vP"
  },
  {
    "id": "1519551061362880513",
    "lang": "in",
    "text": "KEJUARAAN ASIA 2022:Tunggal Putri Indonesia Ini Berhasil Buat Akane Yamaguchi.. https://t.co/ZNXv3BQQMf"
  },
  {
    "id": "1519551060351676417",
    "lang": "in",
    "text": "@wrixlerun @convomf Shotaro itu presiden kedua Indonesia kan?"
  },
  {
    "id": "1519551057919025152",
    "lang": "in",
    "text": "Selamat Siangg 😉 Open Joki Tugas Dan Ulangan Realtime Matematika, Kimia, Bahasa Inggris, Bahasa Indonesia, Bahasa Jepang 🥰\n\n📱 Minat? https://t.co/HChuTpY3ML"
  },
  {
    "id": "1519551053360136192",
    "lang": "in",
    "text": "RT @dianasayangku: Di twitter kita boleh flexing dengan kriteria gaji 2-3 digit. Tapi di dunia nyata, banyak pegawai toko, penjaga counter,…"
  },
  {
    "id": "1519551053301047296",
    "lang": "in",
    "text": "Puan mengingatkan tugas pemerintah untuk melobi Arab Saudi dan memastikan agar Indonesia mendapatkan jumlah kuota haji yang memadai. https://t.co/WKiMGU4WIz"
  },
  {
    "id": "1519551052365778944",
    "lang": "in",
    "text": "RT @Human_B: Malaysia Cabut peraturan Pandemi dan ga pakai scan² lagi.... nah negara Indonesia kok ga bisa?\n@KemenkesRI dan @PBIDI \n\n@VFath…"
  },
  {
    "id": "1519551049178423296",
    "lang": "in",
    "text": "@dinardiaa @NetflixID Ngerasain banget hal gini kalau beres kerja. \nPadahal katanya indonesia menuju metaverse, tapi tranportasi publiknya masih kacau."
  },
  {
    "id": "1519551048251105280",
    "lang": "in",
    "text": "RT @VersaTeal_twt: [BTS 9th Anniversary Fan Song Project by INDONESIAN ARMY]\n\nTentang Project #OneHistoryOneStar:\n\n\"One History One Star\" a…"
  },
  {
    "id": "1519551047500730368",
    "lang": "in",
    "text": "RT @MALAYSIAVIRALL: Jemm kat Indonesia sebab orang balik nak beraya kat kampung. Dulu  Pernah ada kes ada orang mati sebab 2 hari terkandas…"
  },
  {
    "id": "1519551045411565569",
    "lang": "in",
    "text": "RT @MALAYSIAVIRALL: Jemm kat Indonesia sebab orang balik nak beraya kat kampung. Dulu  Pernah ada kes ada orang mati sebab 2 hari terkandas…"
  },
  {
    "id": "1519551040508424192",
    "lang": "in",
    "text": "#BeriTebengan Indonesia - Indonesia, 28/04 23:00, 6 seat, Rp. 200.000, meeting point yang telah d... https://t.co/rYW5OXvUOI @nebengers https://t.co/tEAIfHyHjW"
  },
  {
    "id": "1519551032203784192",
    "lang": "in",
    "text": "RT @elangnusantar4: Ada alasan di balik terus dkejarnya penyelesaian silang sengkarut di tubuh PT Garuda Indonesia Tbk (GIAA). Alasan ini t…"
  },
  {
    "id": "1519551030584774661",
    "lang": "in",
    "text": "RT @bayuarisandee: Lagi di tahap The Daddies kalau menang bersyukur kalau kalah juga gak apa-apa, bukan gak mau support tapi udah banyak ba…"
  },
  {
    "id": "1519551030564102144",
    "lang": "in",
    "text": "RT @dianasayangku: Di twitter kita boleh flexing dengan kriteria gaji 2-3 digit. Tapi di dunia nyata, banyak pegawai toko, penjaga counter,…"
  },
  {
    "id": "1519551030102437888",
    "lang": "in",
    "text": "RT @dianasayangku: Di twitter kita boleh flexing dengan kriteria gaji 2-3 digit. Tapi di dunia nyata, banyak pegawai toko, penjaga counter,…"
  },
  {
    "id": "1519551025127903232",
    "lang": "in",
    "text": "Selamat Siangg 😽 Open Joki Tugas Dan Ulangan Realtime Matematika, Kimia, Bahasa Inggris, Bahasa Indonesia, Bahasa Jepang 😻\n\n📱 Minat? https://t.co/HChuTpY3ML"
  },
  {
    "id": "1519551019264270336",
    "lang": "in",
    "text": "RT @DamarJuniarto: Saya tahu tinggal beberapa hari lagi menuju Lebaran, suasananya sudah gak mendukung, pengen liburan dan rebahan. \n\nTapi…"
  },
  {
    "id": "1519551018622922752",
    "lang": "in",
    "text": "RT @budimandjatmiko: Orang ini salah kamar:\n1. Itu ucapan Bung Karno..Bu Mega mengutipnya\n2. Pernyataan itu u/ Muslim Indonesia (juga Hindu…"
  },
  {
    "id": "1519551017003614208",
    "lang": "in",
    "text": "5. Kakanwil Kemenkumham Sumsel Harun Sulianto: kemudian jg BerAKHLAK (Berorientasi Pelayanan, Akuntabel, Kompeten, Harmonis, Loyal, Adaptif, dan Kolaboratif) untuk mewujudkan Indonesia Maju. \n@Kemenkumham_RI\n@kumhamsumsel \n#KumhamPasti\n#KumhamSumsel"
  },
  {
    "id": "1519551015758200834",
    "lang": "in",
    "text": "RT @dianasayangku: Di twitter kita boleh flexing dengan kriteria gaji 2-3 digit. Tapi di dunia nyata, banyak pegawai toko, penjaga counter,…"
  },
  {
    "id": "1519551015355559937",
    "lang": "in",
    "text": "RT @thumbprintco: @bidadaru @husain_fahasbu Banyak faktor mas, bisa jadi :\n1. kemiskinan struktural\n2. culture indonesia bahwa seseorang yg…"
  },
  {
    "id": "1519551014361497600",
    "lang": "in",
    "text": "RT @detikcom: Kedutaan Besar Amerika Serikat untuk Indonesia saat ini tengah membuka lowongan kerja berbagai macam posisi.  https://t.co/sn…"
  },
  {
    "id": "1519551011236753408",
    "lang": "in",
    "text": "RT @RANGERmounts: Pembagian kaos, saat acara mudik gratis, oleh pemprov DKI, kaos bertuliskan anies baswedan presiden Indonesia, \"menggunka…"
  },
  {
    "id": "1519551009533886464",
    "lang": "in",
    "text": "Pembentukan Partai Mahasiswa Indonesia (PMI) dianggap sebagai upaya menggembosi gerakan mahasiswa. Ketua Umum PMI justru menemui Ketua Dewan Pertimbangan Presiden, Wiranto, pada saat mahasiswa gencar menentang agenda Jokowi tiga periode. #KoranTempo https://t.co/C6wVlEwdk1"
  },
  {
    "id": "1519551000524193792",
    "lang": "in",
    "text": "RT @HopeOrangutan: 🥺🥺 EKSPLOITASI SATWA LIAR SIH INI. YUK BISA YUK NETIZEN INDONESIA LEBIH SELEKTIF DAN CERDAS LAGI BEDAIN TERKAIT INFLUENC…"
  },
  {
    "id": "1519550997659799552",
    "lang": "in",
    "text": "RT @stefanyvonne: Siapa yg selalu pesimis sama prestasi WS tapi liat progress mereka di BAC jadi ada harapan sama daun muda WS Indonesia??…"
  },
  {
    "id": "1519550997164888064",
    "lang": "in",
    "text": "@KompasTV Ironis indonesia punya pemimpim seperti anda\nSungguh kasihan negeri ini"
  },
  {
    "id": "1519550996594053120",
    "lang": "in",
    "text": "Puan menyebut, umat muslim di Indonesia sudah lama menanti agar bisa kembali menunaikan ibadah haji. https://t.co/WKiMGU4WIz"
  },
  {
    "id": "1519550989124390913",
    "lang": "in",
    "text": "RT @MALAYSIAVIRALL: Jemm kat Indonesia sebab orang balik nak beraya kat kampung. Dulu  Pernah ada kes ada orang mati sebab 2 hari terkandas…"
  },
  {
    "id": "1519550987224051712",
    "lang": "in",
    "text": "Selamat Siangg 🤗 Open Joki Tugas Dan Ulangan Realtime Matematika, Kimia, Bahasa Inggris, Bahasa Indonesia, Bahasa Jepang 🧸\n\n📱 Minat? https://t.co/HChuTpY3ML"
  },
  {
    "id": "1519550983868936193",
    "lang": "in",
    "text": "RT @The_RedsIndo: Kita spill deh, betul salah satu admin kita sekarang di UK lagi menempuh pendidikan. admin lainnya lagi kerja di Abu Dhab…"
  },
  {
    "id": "1519550980261486592",
    "lang": "in",
    "text": "“Pemerintah harus bergerak cepat untuk memaksimalkan diplomasi agar Indonesia bisa mendapatkan kuota maksimal,” –Puan Maharani https://t.co/UaZH2CQ0wt"
  },
  {
    "id": "1519550979032895489",
    "lang": "in",
    "text": "RT @jawapos: BMKG Ingatkan Potensi Hujan Lebat di Sejumlah Wilayah Indonesia https://t.co/r5QqvrI3rw"
  },
  {
    "id": "1519550975970709504",
    "lang": "in",
    "text": "RT @BajakSawah22: Yth Ibu Megawati Soekarnoputri,saya bukan kader @PDI_Perjuangan dan juga bukan simpatisan.Tapi saya selaku warga negara I…"
  },
  {
    "id": "1519550950066728960",
    "lang": "in",
    "text": "RT @Retnowonosari: Ketua Umum Ikatan Gus Gus Indonesia (IGGI) KH Ahmad Fahrur Rozi menilai Menteri BUMN Erick Thohir sebagai sosok yang tep…"
  },
  {
    "id": "1519550949089755136",
    "lang": "in",
    "text": "RT @hermawan_devina: Pengen banget supermarket di Indonesia dapat menampilkan harga satuan per satuan unit untuk memudahkan pelanggan membu…"
  },
  {
    "id": "1519550947516502016",
    "lang": "in",
    "text": "Puan menilai pemerintah perlu memastikan persiapan teknis sehingga jemaah haji Indonesia dapat terlayani dengan baik."
  },
  {
    "id": "1519550947285815296",
    "lang": "in",
    "text": "Selamat Siangg 🙋🏻 Open Joki Tugas Dan Ulangan Realtime Matematika, Kimia, Bahasa Inggris, Bahasa Indonesia, Bahasa Jepang 🙆🏻\n\n📚 Minat? https://t.co/HChuTpY3ML"
  },
  {
    "id": "1519550944710897665",
    "lang": "in",
    "text": "RT @HopeOrangutan: 🥺🥺 EKSPLOITASI SATWA LIAR SIH INI. YUK BISA YUK NETIZEN INDONESIA LEBIH SELEKTIF DAN CERDAS LAGI BEDAIN TERKAIT INFLUENC…"
  },
  {
    "id": "1519550943355826177",
    "lang": "in",
    "text": "##BeriTebengan Indonesia - Indonesia, 28/04 23:00, 6 seat, Rp. 200.000, meeting point yang telah d... https://t.co/Rk2I7wBoiZ @nebengers https://t.co/tEAIfHyHjW"
  },
  {
    "id": "1519550942823448576",
    "lang": "in",
    "text": "RT @HopeOrangutan: 🥺🥺 EKSPLOITASI SATWA LIAR SIH INI. YUK BISA YUK NETIZEN INDONESIA LEBIH SELEKTIF DAN CERDAS LAGI BEDAIN TERKAIT INFLUENC…"
  },
  {
    "id": "1519550942655377408",
    "lang": "in",
    "text": "Kepala Negara menyadari bahwa kebijakan pelarangan ekspor bahan baku minyak goreng dan minyak goreng dapat berdampak pada perekonomian Indonesia. Untuk itu, pemerintah akan mencabut larangan tersebut apabila kebutuhan dalam negeri telah terpenuhi. https://t.co/ThQqZhkkOT"
  },
  {
    "id": "1519550940222607360",
    "lang": "in",
    "text": "RT @kumajaas: Seperti biasa, buku2 dijual 📚\n\nAda setumpuk buku, genre campur, ada bahasa Indonesia dan bahasa Inggris, silahkan barang kali…"
  },
  {
    "id": "1519550937723183104",
    "lang": "in",
    "text": "RT @yoongi4ddicted: @BTS_twt GOALS GLOBAL DAN INDONESIA!~\n\npre-made playlist: https://t.co/HkX4nQ29mp\n\nbesok waktu lagunya rilis, langsung…"
  },
  {
    "id": "1519550933859913728",
    "lang": "in",
    "text": "*Silaturahim, menjenguk kampung halaman...*\n\nFenomena mudik Indonesia dikenal hingga mancanegara...\n\nMacet 16 Km dari arah Ibu Kota:\nhttps://t.co/Co2cNHOenZ\n\n #ErickThohirSolusiRakyat"
  },
  {
    "id": "1519550932643880961",
    "lang": "in",
    "text": "RT @BajakSawah22: Yth Ibu Megawati Soekarnoputri,saya bukan kader @PDI_Perjuangan dan juga bukan simpatisan.Tapi saya selaku warga negara I…"
  },
  {
    "id": "1519550931347861505",
    "lang": "in",
    "text": "RT @detikcom: Anak buah Terawan mendirikan organisasi profesi dokter baru yakni Perkumpulan Dokter Seluruh Indonesia (PDSI). Anggotanya waj…"
  },
  {
    "id": "1519550930680643586",
    "lang": "in",
    "text": "Ketua DPR RI Puan Maharani meminta pemerintah Indonesia bergerak cepat untuk mempersiapkan pelaksanaan ibadah haji 2022 dan mengupayakan kuota maksimal. https://t.co/UaZH2CQ0wt"
  },
  {
    "id": "1519550917120380928",
    "lang": "in",
    "text": "RT @Bams_1eng: @GustiMberkahi Ganjar Pranowo Terbaik, kita dukung sebagai penerima tongkat estafet untuk menyongsong INDONESIA EMAS 👏🇮🇩\n#GA…"
  },
  {
    "id": "1519550914498945024",
    "lang": "in",
    "text": "Selamat Siangg 🤩 Open Joki Tugas Dan Ulangan Realtime Matematika, Kimia, Bahasa Inggris, Bahasa Indonesia, Bahasa Jepang 🐣\n\n📚 Minat? https://t.co/HChuTpY3ML"
  },
  {
    "id": "1519550913987641345",
    "lang": "in",
    "text": "RT @budimandjatmiko: Orang ini salah kamar:\n1. Itu ucapan Bung Karno..Bu Mega mengutipnya\n2. Pernyataan itu u/ Muslim Indonesia (juga Hindu…"
  },
  {
    "id": "1519550911143563264",
    "lang": "in",
    "text": "RT @bayuarisandee: Putri KW mengalahkan WS 2 Korea\n\nStephanie Widjaja mengajak rubber An Seyong\n\nKomang Ayu mengajak rubber dan ketat di se…"
  },
  {
    "id": "1519550910396977152",
    "lang": "in",
    "text": "@Didit11310638 @beny_wenda heh.\ngue kelahiran cipayung \nmodal jual motor dan maskawin ortu gue dapet duit 25 jt\ntahun 2007 bakap gw memutuskan pindah ke palembang muba, tungkal ilir, bertak.\nskrang kbon kret bokap gw udh 15 HA. sarng wlet 2 lkasi\nkalo idp dsana susah ngpain brtahan d sna\nindonesia luas oi"
  },
  {
    "id": "1519550909449371648",
    "lang": "in",
    "text": "Apakah nanti bakal muncul kongres dokter Indonesia, atau dewan dokter nasional, atau perkumpulan dokter Indonesia, atau paling deket ikatan dokter Indonesia versi siapa gitu? https://t.co/NnbET9WScT"
  },
  {
    "id": "1519550908115218432",
    "lang": "in",
    "text": "RT @DamarJuniarto: Saya tahu tinggal beberapa hari lagi menuju Lebaran, suasananya sudah gak mendukung, pengen liburan dan rebahan. \n\nTapi…"
  },
  {
    "id": "1519550905712275456",
    "lang": "in",
    "text": "RT @HopeOrangutan: 🥺🥺 EKSPLOITASI SATWA LIAR SIH INI. YUK BISA YUK NETIZEN INDONESIA LEBIH SELEKTIF DAN CERDAS LAGI BEDAIN TERKAIT INFLUENC…"
  },
  {
    "id": "1519550903027593216",
    "lang": "in",
    "text": "RT @hermawan_devina: Pengen banget supermarket di Indonesia dapat menampilkan harga satuan per satuan unit untuk memudahkan pelanggan membu…"
  },
  {
    "id": "1519550897130393600",
    "lang": "in",
    "text": "Alhamdulillah terima kasih Bank Syariah Indonesia atas kontribusinya dalam menyemarakan Gema Ramadhan bersama Yayasan Masjid Cut Meutia Memteng, semoga berkah dan bisnisnya semakin berkembang https://t.co/xcSiu34iA3"
  },
  {
    "id": "1519550896505380864",
    "lang": "in",
    "text": "“Mari kita jalani Bulan Ramadhan yang mulia dan penuh keberkahan ini dengan aktivitas positif, produktif, untuk menyongsong masa depan Indonesia yang lebih baik.”—Puan Maharani"
  },
  {
    "id": "1519550893317713921",
    "lang": "in",
    "text": "RT @tiyaardiani: Harapan Komunitas KN-WK sangat tinggi kepada Ridwan Kamil, jika nantinya terpilih sebagai Presiden Indonesia di 2024.\n\nMer…"
  },
  {
    "id": "1519550883771535362",
    "lang": "in",
    "text": "Diketahui MA mengabulkan uji materi yang dilayangkan Yayasan Konsumen Muslim Indonesia (YMKI). \n\nDengan diterimanya gugatan tersebut, pemerintah harus memastikan vaksin Covid-19 yang diberikan untuk masyarakat mesti dinyatakan halal menurut fatwa Majelis Ulama Indonesia (MUI)."
  },
  {
    "id": "1519550880655486979",
    "lang": "in",
    "text": "Langkah tepat Erick Thohir yang bersinergi dengan Panja Komisi VI DPR RI dalam penyelamatan PT Garuda Indonesia (Persero) Tbk, bisa jadi role model Kementerian lainnya\n\n @erickthohir \n#ErickThohirSolusiRakyat https://t.co/KKhEg1G2R2"
  },
  {
    "id": "1519550880499912705",
    "lang": "in",
    "text": "Puan mengajak seluruh umat Islam pada bulan Ramadan yang mulia dan penuh keberkahan ini dengan aktivitas positif, produktif, untuk menyongsong masa depan Indonesia lebih baik. https://t.co/3wauIADLC9"
  },
  {
    "id": "1519550878348312576",
    "lang": "in",
    "text": "Selamat Siangg 🤗 Open Joki Tugas Dan Ulangan Realtime Matematika, Kimia, Bahasa Inggris, Bahasa Indonesia, Bahasa Jepang 📝\n\n📚 Minat? https://t.co/HChuTpY3ML"
  },
  {
    "id": "1519550869833924608",
    "lang": "in",
    "text": "RT @ibrahimuhf: @utaeeeeee Ini ada ngga yang suka sama aku? Buruan nyatain, sebelum aku follow akun indonesia tanpa pacaran"
  },
  {
    "id": "1519550869020504064",
    "lang": "in",
    "text": "RT @realdonaldmap: INDONESIA!"
  },
  {
    "id": "1519550868437094400",
    "lang": "in",
    "text": "@AREAJULID Simple. Kamu di Indonesia ikut budaya Indonesia. Di Jerman batu ikut budaya Jerman. Jawaban ini tidak bisa dipakai untuk membenarkan aksi tersebut. 👍👌"
  },
  {
    "id": "1519550865434021889",
    "lang": "in",
    "text": "RT @budimandjatmiko: Orang ini salah kamar:\n1. Itu ucapan Bung Karno..Bu Mega mengutipnya\n2. Pernyataan itu u/ Muslim Indonesia (juga Hindu…"
  },
  {
    "id": "1519550864058241025",
    "lang": "in",
    "text": "RT @KipasCosmos_24: @__whalien_52__ @tvindonesiawkwk @txtdrimedia @AREAJULID @txtdrberseragam @txtdrpemerintah @PolJokesID Lho bukannya bia…"
  },
  {
    "id": "1519550863559507968",
    "lang": "in",
    "text": "RT @Sangkuriang5551: APRIL 2022 \nUTANG INDONESIA TOTAL \nsudah mencapai 81,234% dari GDP. \n\nUtang pemerintah + utang BUMN + utang BI mencapa…"
  },
  {
    "id": "1519550862795808768",
    "lang": "in",
    "text": "RT @FaktaBukanAuta: Tahukah anda punyalah kaya Mas Elon (nama Indonesia), harga dia beli Twitter boleh beli 15 kelab bola sepak ternama dun…"
  },
  {
    "id": "1519550862502207488",
    "lang": "in",
    "text": "Survei singkat dibayar mahal, pertama di Indonesia, Klik https://t.co/M88g44UHks"
  },
  {
    "id": "1519550858421485568",
    "lang": "in",
    "text": "RT @AriefImamPoero: Tolong laporkan ke Kemendagri RI, pakai dana apbd Pemprov DKI untuk kampanye pribadi Anies...\n\nMomen Mudik Gratis 11.68…"
  },
  {
    "id": "1519550852041965568",
    "lang": "in",
    "text": "RT @sigitwid: Mudik gratis ini menggunakan dana APBD DKI Jakarta sebesar Rp13,7 miliar. Kalau digunakan untuk kepentingan pribadi bisa dika…"
  },
  {
    "id": "1519550849709744130",
    "lang": "in",
    "text": "bokep latin # \nkorean pornhub # \ndownload video kakek jepang # \ndowdload bokep # \nlink bpkep # \nfree sek jepang # \ngudang video xxx # \nvidio bokef bule # \nvidio ngentot indo # ...  #\nboxep korea # #\ndownload video porno 3gp indonesia # #\ndownload video a… https://t.co/77Fxe8WhmP"
  },
  {
    "id": "1519550849642803201",
    "lang": "in",
    "text": "@hadifianwidjaja @VIVAcoid Intinya kita tunggu saja,akan kmna Indonesia skrg dibawa Jokowi,apa bertahan sampai 2024,atau seperti Soeharto...lengser kprabon!"
  },
  {
    "id": "1519550846853259264",
    "lang": "in",
    "text": "RT @mohmahfudmd: Sy jg tak prnh bilang TNI akan kudeta. Yg sy bilang, di Amerika Latin jika negara tak bs mengatasi perpecahan dan korupsi…"
  },
  {
    "id": "1519550843564879872",
    "lang": "in",
    "text": "RT @imotone: Fenomena kemacetan di tol saat mudik. Sisi positifnya:\n1. Jokowi membangun banyak tol dan saatnya bisa dinikmati banyak pemudi…"
  },
  {
    "id": "1519550843061964800",
    "lang": "in",
    "text": "RT @wangyibee: Daripada koar2 belain influencer yang ono mending nontonin channelnya om chanee kalaweit, orang prancis yang peduli sama sat…"
  },
  {
    "id": "1519550842571223041",
    "lang": "in",
    "text": "12. Kanwil Kemenkumham Sumsel: Kerjasama Indonesia dan China juga semakin menguat pada saat pandemi Covid-19. \n@Kemenkumham_RI\n@PalembangLpka\n#LpkaPalembang"
  },
  {
    "id": "1519550833364324352",
    "lang": "in",
    "text": "RT @HopeOrangutan: 🥺🥺 EKSPLOITASI SATWA LIAR SIH INI. YUK BISA YUK NETIZEN INDONESIA LEBIH SELEKTIF DAN CERDAS LAGI BEDAIN TERKAIT INFLUENC…"
  },
  {
    "id": "1519550832664256513",
    "lang": "in",
    "text": "9. Kanwil Kemenkumham Sumsel: Menkumham Yasonna H. Laoly: namun terkait ekstradisi Indonesia dan China belum memiliki perjanjian. \n@Kemenkumham_RI\n@PalembangLpka\n#LpkaPalembang"
  },
  {
    "id": "1519550831934459904",
    "lang": "in",
    "text": "Mahfud MD semakin gelap mata tak bisa lihat apa2 lagi kecuali hrs dng cara kudeta untuk benahi indonesia stlh didemo para kadrun dr negri asalnya demo minta difasilitasi agar faham kilafah bisa masuk agenda pemerintahan dan dia nggak bisa mengabulkannya, maka smakin buta lah dia"
  },
  {
    "id": "1519550830684168193",
    "lang": "in",
    "text": "@sasalelesale Gapapa sii aslinya cuman bosenn aja😂\nMake emina yg sangat amat cocok dikantong remaja indonesia awossokssksk"
  },
  {
    "id": "1519550828478341121",
    "lang": "in",
    "text": "7. Kanwil Kemenkumham Sumsel: Menkumham dan Duta Besar China juga membahas kerja sama bantuan hukum timbal balik antara Indonesia dan China yang telah disahkan melalui Undang - Undang No. 8 Tahun 2006. \n@Kemenkumham_RI\n@PalembangLpka\n#LpkaPalembang"
  },
  {
    "id": "1519550828058533888",
    "lang": "in",
    "text": "RT @Jalan_Sunyi0523: \"Pemerintah Sadarlah Bahwa Indonesia Bukan Negara Islam, tetapi 90% Rakyat beagama Islam. Kalau Pemerintah Bikin Perat…"
  },
  {
    "id": "1519550826674462720",
    "lang": "in",
    "text": "RT @jstcforemployee: cerita tentang salah satu perusahaan televisi yang dimiliki oleh konglomerat indonesia berlogo warna merah."
  },
  {
    "id": "1519550826620276736",
    "lang": "in",
    "text": "6. Kanwil Kemenkumham Sumsel: Duta Besar China: Tentunya perlu adanya kerja sama antara Indonesia dengan China dalam menangani isu kejahatan transnasional ini. \n@Kemenkumham_RI\n@PalembangLpka\n#LpkaPalembang"
  },
  {
    "id": "1519550826343067649",
    "lang": "in",
    "text": "RT @enop_ancha: Sebagaimana Imbauan dari Presiden Republik Indonesia Joko Widodo.\n**\nErick Thohir menyampaikan, Mudik Gratis Bersama BUMN i…"
  },
  {
    "id": "1519550822857981952",
    "lang": "in",
    "text": "4. Kanwil Kemenkumham Sumsel: Menkumham Yasonna H. Laoly: Untuk itu, Indonesia dan China perlu meningkatkan kerja sama dan koordinasi dalam ruang lingkup penegakan hukum.\n@Kemenkumham_RI\n@PalembangLpka\n#LpkaPalembang"
  },
  {
    "id": "1519550819296808961",
    "lang": "in",
    "text": "Info Mudik: Mudik Massal Jelang Lebaran Juga Dilakukan Warga India Seperti di Indonesia – https://t.co/fjhwMHSYYW” – Media Informasi – https://t.co/FGFAnfl4fF https://t.co/ACfhWpzOK3"
  },
  {
    "id": "1519550818542047233",
    "lang": "in",
    "text": "Rilis 3 (28/4) \n\n1. Kanwil Kemenkumham Sumsel: Menteri Hukum dan HAM (Menkumham), Yasonna H. Laoly menerima kunjungan kehormatan dari Duta Besar China untuk Indonesia,Lu Kang, Rabu (27/4/2022)\n@Kemenkumham_RI\n@kumhamsumsel \n#KumhamPasti\n#KumhamSumsel\n@PalembangLpka\n#LpkaPalembang"
  },
  {
    "id": "1519550810660638720",
    "lang": "in",
    "text": "Joktug! (Tema dari aku) drop FEE buat paper isinya \n1. Abstrak (250 kata, berbahasa inggris dan indonesia)\n2. Pendahuluan\n2. Pembahasan\n3. Penutup"
  },
  {
    "id": "1519550808433782784",
    "lang": "in",
    "text": "RT @dearzest: Kepala BP2MI Benny Rhamdani dinilai mampu menorehkan beragam prestasi bagi lembaga, secara langsung dirasakan oleh pekerja mi…"
  },
  {
    "id": "1519550805741019136",
    "lang": "in",
    "text": "RT @sigitwid: Apakah Pak @aniesbaswedan tahu soal kaos ini?\n\nMudik gratis ini menggunakan dana APBD DKI Jakarta sebesar Rp 13,7 miliar, kal…"
  },
  {
    "id": "1519550804394319873",
    "lang": "in",
    "text": "RT @DiposuroP: Dear : PKI ( Perkumpulan Kadrun Indonesia ) \n\nCoba kalian bilang ini semua para oknum drun..😂😂 https://t.co/0yFsGycQYC"
  },
  {
    "id": "1519550793661108229",
    "lang": "in",
    "text": "Hipotesa:\nJika #LBPPresidenRI, Indonesia sejahtera dalam 10 tahun.\n\nhttps://t.co/HK509LG70X"
  },
  {
    "id": "1519550793099399169",
    "lang": "in",
    "text": "RT @mohmahfudmd: Sy jg tak prnh bilang TNI akan kudeta. Yg sy bilang, di Amerika Latin jika negara tak bs mengatasi perpecahan dan korupsi…"
  },
  {
    "id": "1519550792486686720",
    "lang": "in",
    "text": "@Hunterjagar3 @AnakLolina2 Inilah gubernur ter #bodoh yg pernah ada di Indonesia dan juga gubernur yg #doyan_ngibul alias #tukang_bohong dengan kata lainnya #munafikun"
  },
  {
    "id": "1519550782906851331",
    "lang": "in",
    "text": "Silaturahim, menjenguk kampung halaman...\n\nFenomena mudik Indonesia dikenal hingga mancanegara...\n\nMacet 16 Km dari arah Ibu Kota.\nhttps://t.co/Co2cNHOenZ\n\nLebaran 1 Syawal mau banget di kampung halaman"
  },
  {
    "id": "1519550778016296960",
    "lang": "in",
    "text": "RT @InsouthSoun: gue tau akun gue flop, tapi gue mau bikin #giveaway photocard Gfriend and Astro dan album day6 yang The Book Of Us : The D…"
  },
  {
    "id": "1519550768906260480",
    "lang": "in",
    "text": "RT @DiposuroP: Intoleransi yg yg sptnya akan terus dipelihara demi kepentingan orang\" yg gila kekuasaan di indonesia\n\nPara pengkhianat bhin…"
  },
  {
    "id": "1519550768105201665",
    "lang": "in",
    "text": "Pemerataan pembangunan di kawasan Indonesia bagian Barat dan Timur lewat pembangunan IKN.\n@kemkominfo @PlateJohnny https://t.co/k4Wd0gtkgp"
  },
  {
    "id": "1519550766708445184",
    "lang": "in",
    "text": "RT @MoelyonovDjalil: Menjelang 1 Syawal Cikampek cantik banget pemandangannya. Dari semalem saat jumlah orang miskin &amp; pengangguran semakin…"
  },
  {
    "id": "1519550764737515520",
    "lang": "in",
    "text": "RT @wangyibee: Daripada koar2 belain influencer yang ono mending nontonin channelnya om chanee kalaweit, orang prancis yang peduli sama sat…"
  },
  {
    "id": "1519550761482420224",
    "lang": "in",
    "text": "Alhamdulilah. Aku dapat melakukan kebaikan. Bisa ngelike cuitan @elonmusk walau gak ngerti yang dia tulis.\n\nBelajar sok gaya kenal @elonmusk seperti yang dilakukan seseorang yang ngaku PERDANA MENTERI Indonesia ituuuuuu"
  },
  {
    "id": "1519550760702590977",
    "lang": "in",
    "text": "RT @wangyibee: Daripada koar2 belain influencer yang ono mending nontonin channelnya om chanee kalaweit, orang prancis yang peduli sama sat…"
  },
  {
    "id": "1519550754167558144",
    "lang": "in",
    "text": "RT @tiyaardiani: Harapan Komunitas KN-WK sangat tinggi kepada Ridwan Kamil, jika nantinya terpilih sebagai Presiden Indonesia di 2024.\n\nMer…"
  },
  {
    "id": "1519550747716702208",
    "lang": "in",
    "text": "YOU KNOW WHAT FINN BENER ANJING, SELERA KONSUMEN INDONESIA JELEK MAMPUS, FAZZIO AJA DIBILANG KAKU DAN JELEK, LU KIRA DESAIN MOTOR JEPANG DI INDONESIA YANG LAIN BAGUS GITU?!!???"
  },
  {
    "id": "1519550747255652354",
    "lang": "in",
    "text": "RT @detikcom: Anak buah Terawan mendirikan organisasi profesi dokter baru yakni Perkumpulan Dokter Seluruh Indonesia (PDSI). Anggotanya waj…"
  },
  {
    "id": "1519550739810447360",
    "lang": "in",
    "text": "Acara cabut baiat merupakan pendekatan pemerintah untuk mengembalikan saudara-saudara yang tertipu oleh kelompok Negara Islam Indonesia.  #densus88antiteror https://t.co/K2ZVXXzR3C"
  },
  {
    "id": "1519550739248390144",
    "lang": "in",
    "text": "@MoelyonovDjalil Disaat pembangunan tol berjalan, tidak sedikit dari \"mereka\" menyatakan menolak makan infrastruktur. Dan \"mereka\" membuktikannya, jalan tol kosong melompong.\nIndonesia memang keren 🇮🇩\n\nsalim siang Pakdhe 🙏"
  },
  {
    "id": "1519550732923711488",
    "lang": "in",
    "text": "RT @Cantika82104633: Ada yg aneh kah dari ke 2 foto tsb?\nYg aneh justru mereka2 yg ribut, krn mereka iri Indonesia di terima oleh Elon Musk…"
  },
  {
    "id": "1519550728242483200",
    "lang": "in",
    "text": "RT @dianasayangku: Di twitter kita boleh flexing dengan kriteria gaji 2-3 digit. Tapi di dunia nyata, banyak pegawai toko, penjaga counter,…"
  },
  {
    "id": "1519550726287990784",
    "lang": "in",
    "text": "Sobat BUMN,\n\nBULOG siap salurkan kedelai pada harga lebih rendah kepada pengrajin tahu tempe melalui Program Bantuan Penggantian kepada Koperasi Produsen Tahu Tempe Indonesia (KOPTI) di Jawa Barat. \n\n#StokKedelaiBULOGTerjaga https://t.co/7wpTMLpkhg"
  },
  {
    "id": "1519550725365596160",
    "lang": "in",
    "text": "Hasil Badminton Asia Championships 2022 Hari ini: Pramel &amp; Jojo Menang D... https://t.co/oYsJADmiLm lewat @YouTube \nHasil #BAC2022 Day3 atau R16 hari ini.\nJojo dan #Pramel Menang sementara itu #Daddies harus tersingkir. untuk sementara 4 Wakil Indonesia lolos ke 8 Besar #BAC2022"
  },
  {
    "id": "1519550722307633152",
    "lang": "in",
    "text": "@4nneve kalo Indonesia gak mungkin, hatinya sudah pada sakit 😆"
  },
  {
    "id": "1519550709921767425",
    "lang": "in",
    "text": "RT @korantempo: Partai Mahasiswa resmi tercatat di Kementerian Hukum dan HAM. Proses pembentukan Partai Mahasiswa Indonesia yang cepat dipe…"
  },
  {
    "id": "1519550709108449280",
    "lang": "in",
    "text": "RT @bayuarisandee: Putri KW mengalahkan WS 2 Korea\n\nStephanie Widjaja mengajak rubber An Seyong\n\nKomang Ayu mengajak rubber dan ketat di se…"
  },
  {
    "id": "1519550706323050496",
    "lang": "in",
    "text": "Baksos Partai Parsindo (Partai Swara Rakyat Indonesia). Mensyukuri yang sedikit dan berbagi. https://t.co/G2UEpgUZzn"
  },
  {
    "id": "1519550687914323968",
    "lang": "in",
    "text": "RT @jstcforemployee: cerita tentang salah satu perusahaan televisi yang dimiliki oleh konglomerat indonesia berlogo warna merah."
  },
  {
    "id": "1519550685141815296",
    "lang": "in",
    "text": "RT @Jogja_Uncover: 2 bibit siklon menjepit Indonesia https://t.co/nVdzRmMlVW"
  },
  {
    "id": "1519550682885287936",
    "lang": "in",
    "text": "RT @budimandjatmiko: Orang ini salah kamar:\n1. Itu ucapan Bung Karno..Bu Mega mengutipnya\n2. Pernyataan itu u/ Muslim Indonesia (juga Hindu…"
  },
  {
    "id": "1519550682202001408",
    "lang": "in",
    "text": "RT @HeriSuwondo2: Kondisi Menurun, Hendropriyono Dirawat secara Intensif di RS. Doakan saja yg TERBAIK buat dia &amp; bangsa Indonesia🙏🙏🙏"
  },
  {
    "id": "1519550679010136064",
    "lang": "in",
    "text": "LIBURAN VLOG KE BANTEN || TRAVELING MURAH || NAIK GUNUNG || PANDEGLANG B... \n\nhttps://t.co/YvVFGVYqoX \n\nlewat @YouTube #youtube #YouTuber #banten #pandeglang #indonesiacantik #Indonesia #wonderland #WonderfulIndonesia"
  },
  {
    "id": "1519550672487690240",
    "lang": "in",
    "text": "RT @HopeOrangutan: 🥺🥺 EKSPLOITASI SATWA LIAR SIH INI. YUK BISA YUK NETIZEN INDONESIA LEBIH SELEKTIF DAN CERDAS LAGI BEDAIN TERKAIT INFLUENC…"
  },
  {
    "id": "1519550670008815616",
    "lang": "in",
    "text": "@sanchujace Kamu inget baca di mana? Barusan baca di disdukcapil cuma sekadar memang akan jadi smart card multifungsi bisa jadi kartu debet, blt, dsbnya. Ada bentuk smartcardnya karena tersimpan chip dan gak semua warga indonesia saat itu mengerti kalau langsung bentuk digitalnya."
  },
  {
    "id": "1519550661418885120",
    "lang": "in",
    "text": "RT @dianasayangku: Di twitter kita boleh flexing dengan kriteria gaji 2-3 digit. Tapi di dunia nyata, banyak pegawai toko, penjaga counter,…"
  },
  {
    "id": "1519550657518530560",
    "lang": "in",
    "text": "RT @ay4m7ago: @detikcom Sekelas dokter yg nota bene otaknya encer bisa berfikir, masih mau di susupi politik pecah belah, dan siap2 sebenta…"
  },
  {
    "id": "1519550656906141696",
    "lang": "in",
    "text": "Udah tenar ya mbak nyenggol \nMakanya baru minta maaf\nBasi mbak\nSama aja kayak org2 Indonesia\nBikin ulah dulu\nKlarifikasi nya belakangan https://t.co/TONg9K75N4"
  },
  {
    "id": "1519550655081619456",
    "lang": "in",
    "text": "RT @maspiyuaja: RESMI! Saingan IDI... Perkumpulan Dokter Seluruh Indonesia (PDSI) Dideklarasikan Hari Ini, Ketuanya Brigjen TNI (purn) http…"
  },
  {
    "id": "1519550651751333888",
    "lang": "in",
    "text": "Respons PSSI soal Undangan Bertanding Bangladesh untuk Timnas Indonesia di FIFA Matchday Juni 2022 https://t.co/0BVO1rj5k1\n\n#BanggaSepakBolaKita"
  },
  {
    "id": "1519550650316582913",
    "lang": "in",
    "text": "RT @jeongwooorld: [🇮🇩Indonesia trans]\nℝ𝔼𝔻 ℝ𝕀𝔻𝕀ℕ𝔾 𝕎𝕆𝕆\n2022 JEONGWOO Birthday Project\n\nHalo teume INA! Untuk donasi silahkan cek detail berik…"
  },
  {
    "id": "1519550648013914112",
    "lang": "in",
    "text": "RT @jstcforemployee: cerita tentang salah satu perusahaan televisi yang dimiliki oleh konglomerat indonesia berlogo warna merah."
  },
  {
    "id": "1519550647367966720",
    "lang": "in",
    "text": "RT @_Vaniaokta: Ikatan Gus Gus Indonesia (IGGI) dukung @erickthohir maju di pilpres 2024 yang menyatakan dan menilai figur Erick Thohir seb…"
  },
  {
    "id": "1519550646499782659",
    "lang": "in",
    "text": "Ucapan Selamat Hari Raya Idul Fitri 1443 H Terbaru 2022  -https://t.co/qnsf8RXldR\n\n#idulfitri2022 #Lebaran2022 #lebaran"
  },
  {
    "id": "1519550642142212097",
    "lang": "in",
    "text": "RT @jstcforemployee: cerita tentang salah satu perusahaan televisi yang dimiliki oleh konglomerat indonesia berlogo warna merah."
  },
  {
    "id": "1519550639579484160",
    "lang": "in",
    "text": "5. Head of Agreement (HoA) teknologi elektronika pertahanan antara PT Len Indonesia (Persero) dan Thales International SAS, France\n6. Memorandum of Understanding (MoU) produksi bersama produk armoured amphibious assault vehicle antara PT Pindad dan FNSS Savunma Sistemieri, Turki."
  },
  {
    "id": "1519550639050682368",
    "lang": "in",
    "text": "RT @Juragantajirrr: Dari seluruh kalangan masyarakat Indonesia, terus memberikan dukungan kepada beliau menteri BUMN @erickthohir \n#ErickTh…"
  },
  {
    "id": "1519550637830447105",
    "lang": "in",
    "text": "Respons PSSI soal Undangan Bertanding Bangladesh untuk Timnas Indonesia di FIFA Matchday Juni 2022 https://t.co/5wkbcNKOdg\n\n#BanggaSepakBolaKita"
  },
  {
    "id": "1519550636471164928",
    "lang": "in",
    "text": "@sasasayatusa_ Ayo TNI n Polri garda terdepan Indonesia... untuk menyelamatkan Papua dari kelompok separatis teroris Papua....  #PenundaanPemilu #Tolak3Periode"
  },
  {
    "id": "1519550633845886977",
    "lang": "in",
    "text": "RT @detikcom: Anak buah Terawan mendirikan organisasi profesi dokter baru yakni Perkumpulan Dokter Seluruh Indonesia (PDSI). Anggotanya waj…"
  },
  {
    "id": "1519550632486600706",
    "lang": "in",
    "text": "RT @TxtdariHI: Ini bisa jadi peluang besar buat Indonesia. Manfaatin presidensi G20 buat buka ruang dialog bagi Rusia dengan Ukraina sekali…"
  },
  {
    "id": "1519550624852942849",
    "lang": "in",
    "text": "Hasil Akhir Badminton Asia Championship: China Kalah, Ganda Campuran Indonesia ke Perempat Final https://t.co/Nk0PZp3UdQ"
  },
  {
    "id": "1519550624811352064",
    "lang": "in",
    "text": "RT @meeayusri: @MALAYSIAVIRALL Real eh meninggal sbb jem 😭😭\n\nhttps://t.co/Uc0dYcjdox"
  },
  {
    "id": "1519550617903308802",
    "lang": "in",
    "text": "RT @DamarJuniarto: Saya tahu tinggal beberapa hari lagi menuju Lebaran, suasananya sudah gak mendukung, pengen liburan dan rebahan. \n\nTapi…"
  },
  {
    "id": "1519550617639092224",
    "lang": "in",
    "text": "@sasasayatusa_ Cantik yang ini dong,penampilannya dewasa yang sesuai. Mukanya cantik Indonesia,classy. Ayu ayu gimana gitu.  #PenundaanPemilu #Tolak3Periode"
  },
  {
    "id": "1519550616917270528",
    "lang": "in",
    "text": "RT @Juragantajirrr: BANDUNG - Relawan Erick Thohir Sahabat Indonesia (ETOS) Jawa Barat menyatakan dukungannya terhadap Menteri Badan Usaha…"
  },
  {
    "id": "1519550609728282688",
    "lang": "in",
    "text": "@ZelenskyyUa @jokowi @g20org Semoga ada solusi nya nanti di indonesia"
  },
  {
    "id": "1519550609221091328",
    "lang": "in",
    "text": "5. Kakanwil Kemenkumham Sumsel Harun Sulianto: kemudian jg BerAKHLAK (Berorientasi Pelayanan, Akuntabel, Kompeten, Harmonis, Loyal, Adaptif, dan Kolaboratif) untuk mewujudkan Indonesia Maju. \n@Kemenkumham_RI\n@PalembangLpka\n#LpkaPalembang"
  },
  {
    "id": "1519550608487104512",
    "lang": "in",
    "text": "RT @Kemdikbud_RI: #SahabatDikbud, yuk, ikuti #SilaturahmiMerdekaBelajar dengan tema \"Wujudkan Mimpi Bersama Beasiswa Pendidikan Indonesia”,…"
  },
  {
    "id": "1519550606536429569",
    "lang": "in",
    "text": "RT @bellydupling: bismillah 9 wakil dari tim badminton indonesia masuk ke QF di badminton asia championship"
  },
  {
    "id": "1519550600312070144",
    "lang": "in",
    "text": "Luarr...biasa sopanantun pak Anies melayani rakyat Indonesia beda dengan yg onoh...ga ada sopan-sopan nya menjijihkan https://t.co/ehBJTNeogK"
  },
  {
    "id": "1519550599787794434",
    "lang": "in",
    "text": "RT @MALAYSIAVIRALL: Jemm kat Indonesia sebab orang balik nak beraya kat kampung. Dulu  Pernah ada kes ada orang mati sebab 2 hari terkandas…"
  },
  {
    "id": "1519550599326433280",
    "lang": "in",
    "text": "@empathysafe bahasa indonesia"
  },
  {
    "id": "1519550597288308736",
    "lang": "in",
    "text": "RT @HopeOrangutan: 🥺🥺 EKSPLOITASI SATWA LIAR SIH INI. YUK BISA YUK NETIZEN INDONESIA LEBIH SELEKTIF DAN CERDAS LAGI BEDAIN TERKAIT INFLUENC…"
  },
  {
    "id": "1519550596897853441",
    "lang": "in",
    "text": "@sasasayatusa_ Dan Alhamdulillah,anak saya menjadi salah satu yang mengikuti vaksin.semoga Indonesia makin sehat dan kuat  #PenundaanPemilu #Tolak3Periode"
  },
  {
    "id": "1519550595660918785",
    "lang": "in",
    "text": "RT @MALAYSIAVIRALL: Jemm kat Indonesia sebab orang balik nak beraya kat kampung. Dulu  Pernah ada kes ada orang mati sebab 2 hari terkandas…"
  },
  {
    "id": "1519550591227527169",
    "lang": "in",
    "text": "@Menlu_RI Semoga Presiden Zelensky bisa hadir plus Indonesia mendamaikan. https://t.co/uT6pQJuufp"
  },
  {
    "id": "1519550589268467712",
    "lang": "in",
    "text": "RT @jstcforemployee: cerita tentang salah satu perusahaan televisi yang dimiliki oleh konglomerat indonesia berlogo warna merah."
  },
  {
    "id": "1519550589042331648",
    "lang": "in",
    "text": "RT @budimandjatmiko: Orang ini salah kamar:\n1. Itu ucapan Bung Karno..Bu Mega mengutipnya\n2. Pernyataan itu u/ Muslim Indonesia (juga Hindu…"
  },
  {
    "id": "1519550586261102596",
    "lang": "in",
    "text": "RT @dianasayangku: Di twitter kita boleh flexing dengan kriteria gaji 2-3 digit. Tapi di dunia nyata, banyak pegawai toko, penjaga counter,…"
  },
  {
    "id": "1519550577486995457",
    "lang": "in",
    "text": "3. Kontrak MRO modernisasi 12 unit pesawat C130 antara PT Dirgantara Indonesia dan Kementerian Pertahanan\n4. Kesepakatan untuk kerjasama MRO peningkatan kemampuan dan modernisasi kapal perang TNI AL antara PT PAL Indonesia dan Kementerian Pertahanan"
  },
  {
    "id": "1519550574512861185",
    "lang": "in",
    "text": "*Silaturahim, menjenguk kampung halaman...*\n\nFenomena mudik Indonesia dikenal hingga mancanegara...\n\nMacet 16 Km dari arah Ibu Kota:\nhttps://t.co/Co2cNHOenZ\n\nPuan Maharani Cikampek #EkstraBantuin"
  },
  {
    "id": "1519550570105044992",
    "lang": "in",
    "text": "@__AnakKolong Miris sekali lihat hukum di Indonesia..gk berani periksa keluarga CIKEAS😁😁😁😁"
  },
  {
    "id": "1519550569274568709",
    "lang": "in",
    "text": "RT @MALAYSIAVIRALL: Jemm kat Indonesia sebab orang balik nak beraya kat kampung. Dulu  Pernah ada kes ada orang mati sebab 2 hari terkandas…"
  },
  {
    "id": "1519550567831732224",
    "lang": "in",
    "text": "RT @nananetcitizen: @BadmintonTalk posting this because everyone should know that Komang Ayu Cahya Dewi, WS INA yg saat ini ada di ranking…"
  },
  {
    "id": "1519550566770561025",
    "lang": "in",
    "text": "RT @bachrum_achmadi: Gengsi dong bos ngemis ke investor spy dtg ke Indonesia, mo tarok dmn muka kita klo mrk ga minat.\n\nMending kluarin yg…"
  },
  {
    "id": "1519550560185483264",
    "lang": "in",
    "text": "RT @bayuarisandee: Putri KW mengalahkan WS 2 Korea\n\nStephanie Widjaja mengajak rubber An Seyong\n\nKomang Ayu mengajak rubber dan ketat di se…"
  },
  {
    "id": "1519550558193221632",
    "lang": "in",
    "text": "RT @BorneoWolf: @DKIJakarta , mohon penjelasannya dengan tegas.\n\nApakah program mudik ini murni program Pemprov DKI Jakarta yg dibiayai APB…"
  },
  {
    "id": "1519550553743032320",
    "lang": "in",
    "text": "RT @infoBMKG: Halo Sobat BMKG,\n\nBeberapa provinsi di Indonesia esok hari berada dalam kategori \"Siaga dan Waspada\" terhadap bencana hidrome…"
  },
  {
    "id": "1519550543366361088",
    "lang": "in",
    "text": "RT @labanux: Delegasi Indonesia datang ke Tesla dgn pakaian rapih, berjas, rambut klimis, nawarin kerjasama buat penyediaan &amp; pemrosesan ni…"
  },
  {
    "id": "1519550541566644224",
    "lang": "in",
    "text": "@panca66 Mohon maaf di infokan bagi para rakyat Indonesia, karna yg berhak dan berwenang untuk mengambil keputusan untuk ekpor di stop atau tidak adalah bapak lord luhut binsar panjaitan. Selain lord luhut, tidak ada yg berhak mengambil keputusan."
  },
  {
    "id": "1519550533971103746",
    "lang": "in",
    "text": "RT @jstcforemployee: cerita tentang salah satu perusahaan televisi yang dimiliki oleh konglomerat indonesia berlogo warna merah."
  },
  {
    "id": "1519550531030577153",
    "lang": "in",
    "text": "RT @HopeOrangutan: 🥺🥺 EKSPLOITASI SATWA LIAR SIH INI. YUK BISA YUK NETIZEN INDONESIA LEBIH SELEKTIF DAN CERDAS LAGI BEDAIN TERKAIT INFLUENC…"
  },
  {
    "id": "1519550527784484865",
    "lang": "in",
    "text": "RT @LurahIstana: Presiden melarang namun menterinya meyatakan tetap melanjutkan.marwah presiden itu dibawah menteri di indonesia saat ini.k…"
  },
  {
    "id": "1519550518061780992",
    "lang": "in",
    "text": "RT @Arindra__: Dukungan yg dbrikan oleh Panitia Kerja (Panja) Komisi VI DPR dlm menyelamatkan PT Garuda Indonesia (Persero) Tbk menunjukkan…"
  },
  {
    "id": "1519550511053033473",
    "lang": "in",
    "text": "@littlemiawmiaww mindset iki kudu dikoar koarne se indonesia raya merdeka tahun 1945 sih 😔"
  },
  {
    "id": "1519550497816195072",
    "lang": "in",
    "text": "RT @dianasayangku: Di twitter kita boleh flexing dengan kriteria gaji 2-3 digit. Tapi di dunia nyata, banyak pegawai toko, penjaga counter,…"
  },
  {
    "id": "1519550494267834369",
    "lang": "in",
    "text": "RT @budimandjatmiko: Orang ini salah kamar:\n1. Itu ucapan Bung Karno..Bu Mega mengutipnya\n2. Pernyataan itu u/ Muslim Indonesia (juga Hindu…"
  },
  {
    "id": "1519550488823304195",
    "lang": "in",
    "text": "RT @martsha_ca: @evylagi Loh loh.. \n1. Popo bukan transpuan, dia masih cowo cmn penampilannya doang yg kayak cewe.\n2. Ini Indonesia bukan J…"
  },
  {
    "id": "1519550485799514112",
    "lang": "in",
    "text": "Puncak Arus Mudik Lebaran 28, 29, 30 April 2022: Jawa Tengah Tujuan Utama Terbanyak yaitu 23,5 Juta Orang\n#Mudik2022 #mudikberkahtokocrypto #infomudik2022 #lebaran #idulfitri #Lebaran2022 #idulfitri2022 #Indonesia #indoviral #news \nhttps://t.co/z4hGnKGoaj"
  },
  {
    "id": "1519550483538780160",
    "lang": "in",
    "text": "RT @Sunwoobulol: @convomf Sayang. KAMI PUTRA DAN PUTRI INDONESIA, MENJUNJUNG BAHASA PERSATUAN! BAHASA INDONESIA!"
  },
  {
    "id": "1519550479302557702",
    "lang": "in",
    "text": "RT @dianasayangku: Di twitter kita boleh flexing dengan kriteria gaji 2-3 digit. Tapi di dunia nyata, banyak pegawai toko, penjaga counter,…"
  },
  {
    "id": "1519550478631448576",
    "lang": "in",
    "text": "@rachellouisa__ @tanyakanrl betul😭tapi ntar katanya kan di Indonesia ga cuma muslim doang, kalo emg mau bebas ya di toilet sendiri aja. Jadi bingung akutuh :("
  },
  {
    "id": "1519550472322883584",
    "lang": "in",
    "text": "RT @detikcom: Anak buah Terawan mendirikan organisasi profesi dokter baru yakni Perkumpulan Dokter Seluruh Indonesia (PDSI). Anggotanya waj…"
  },
  {
    "id": "1519550471484370945",
    "lang": "in",
    "text": "RT @MALAYSIAVIRALL: Jemm kat Indonesia sebab orang balik nak beraya kat kampung. Dulu  Pernah ada kes ada orang mati sebab 2 hari terkandas…"
  },
  {
    "id": "1519550471127543809",
    "lang": "in",
    "text": "RT @Sunwoobulol: @convomf Sayang. KAMI PUTRA DAN PUTRI INDONESIA, MENJUNJUNG BAHASA PERSATUAN! BAHASA INDONESIA!"
  },
  {
    "id": "1519550464500838403",
    "lang": "in",
    "text": "RT @jstcforemployee: cerita tentang salah satu perusahaan televisi yang dimiliki oleh konglomerat indonesia berlogo warna merah."
  },
  {
    "id": "1519550462361747457",
    "lang": "in",
    "text": "RT @HopeOrangutan: 🥺🥺 EKSPLOITASI SATWA LIAR SIH INI. YUK BISA YUK NETIZEN INDONESIA LEBIH SELEKTIF DAN CERDAS LAGI BEDAIN TERKAIT INFLUENC…"
  },
  {
    "id": "1519550459505442816",
    "lang": "in",
    "text": "@minegyuslife Hooh jalan” keliling indonesia"
  },
  {
    "id": "1519550452987498496",
    "lang": "in",
    "text": "RT @HopeOrangutan: 🥺🥺 EKSPLOITASI SATWA LIAR SIH INI. YUK BISA YUK NETIZEN INDONESIA LEBIH SELEKTIF DAN CERDAS LAGI BEDAIN TERKAIT INFLUENC…"
  },
  {
    "id": "1519550439506980864",
    "lang": "in",
    "text": "RT @HopeOrangutan: 🥺🥺 EKSPLOITASI SATWA LIAR SIH INI. YUK BISA YUK NETIZEN INDONESIA LEBIH SELEKTIF DAN CERDAS LAGI BEDAIN TERKAIT INFLUENC…"
  },
  {
    "id": "1519550426013900800",
    "lang": "in",
    "text": "@sadirraa Gini aja,klian ributkan kan mnrut kalian kaum kelompok paling sayang satwa dan alam Indonesia, nah gua tanya tindakan nyata kalian perbuat selain ngebacot dan penggiringan opini trus ditamengin alasan kampanye perlindungan satwa dan alam, apa tindakan nyatanya? 😂"
  },
  {
    "id": "1519550422012559360",
    "lang": "in",
    "text": "RT @27_dalbo: Perkumpulan Dokter Seluruh Indonesia (PDSI)\nResmi Dideklarasikan, Klaim Sudah Diakui Kemenkumham\nRabu (27/4/2022)\n\nKetum PDSI…"
  },
  {
    "id": "1519550419617611777",
    "lang": "in",
    "text": "RT @korantempo: Partai Mahasiswa resmi tercatat di Kementerian Hukum dan HAM. Proses pembentukan Partai Mahasiswa Indonesia yang cepat dipe…"
  },
  {
    "id": "1519550417163927552",
    "lang": "in",
    "text": "@jaykyungjun hii! i'm from indonesia, hbu?"
  },
  {
    "id": "1519550415842340864",
    "lang": "in",
    "text": "bin secara bahasa itu artinya bermakna anak laki-laki. maka saya tulis, rafatthar bin Raffi dan Nagita artinya anak Raffi sebagai ayahnya dan Nagita sebagai ibunya. adapun soal bin ke ayah itu soal lain dan saya tak bahas itu. \n\nberat Indonesia.~ https://t.co/cYxhByEWJn"
  },
  {
    "id": "1519550403255304197",
    "lang": "in",
    "text": "RT @maspiyuaja: RESMI! Saingan IDI... Perkumpulan Dokter Seluruh Indonesia (PDSI) Dideklarasikan Hari Ini, Ketuanya Brigjen TNI (purn) http…"
  },
  {
    "id": "1519550403217551362",
    "lang": "in",
    "text": "Kan dibilang gak persija gak makan. Yang gatau Bola aja jadi ikut ikutan yaa gimana prinsip orang Indonesia begitu tau apa ngga nya yang penting ikut ikutan bang Joy 😂😂 https://t.co/EdrvWa87zV"
  },
  {
    "id": "1519550395990781952",
    "lang": "in",
    "text": "RT @Dihatilenk: Bangsa Indonesia Sudah Sepatutnya Peduli Kepada Palestina, Karena Berkat Perjuangan Kedua Tokoh Ulama Ini Telah Banyak yang…"
  },
  {
    "id": "1519550380346327040",
    "lang": "in",
    "text": "RT @sigitwid: Apakah Pak @aniesbaswedan tahu soal kaos ini?\n\nMudik gratis ini menggunakan dana APBD DKI Jakarta sebesar Rp 13,7 miliar, kal…"
  },
  {
    "id": "1519550377284505600",
    "lang": "in",
    "text": "RT @BERKARYA_NET: Coba chek, bisa jadi di lambung kapal mereka ada tulisan : MILIK PRIBUMI. Mangkanya berani bgd, mereka 😋\nhttps://t.co/d2w…"
  },
  {
    "id": "1519550373366800386",
    "lang": "in",
    "text": "RT @detikcom: Kedutaan Besar Amerika Serikat untuk Indonesia saat ini tengah membuka lowongan kerja berbagai macam posisi.  https://t.co/sn…"
  },
  {
    "id": "1519550370523287552",
    "lang": "in",
    "text": "RT @Abaaah: Dress code yg digunakan tuan rumah saat menyambut tamu adalah bahasa tubuh yg mencerminkan tingkat penghormatan tuan rumah terh…"
  },
  {
    "id": "1519550365867606016",
    "lang": "in",
    "text": "Pembagian kaos \"Anies Baswedan Presiden Indonesia\" Dalam acara Mudik gratis dengan menggunakan APBD #DKIJakarta dilakukan oleh Anies sendiri. \nCc @KPK_RI @KejaksaanRI \nIndikasi penggunaan APBD untuk kepentingan pribadi? \n\nSource IG @Cyber4RI https://t.co/V9J9XvgTUr"
  },
  {
    "id": "1519550361669091329",
    "lang": "in",
    "text": "RT @jstcforemployee: cerita tentang salah satu perusahaan televisi yang dimiliki oleh konglomerat indonesia berlogo warna merah."
  },
  {
    "id": "1519550360222060545",
    "lang": "in",
    "text": "RT @nashirr27: Khilafah Tahririyah ala HTI dan NII, adalah dua bandit agama yang ingin mengganggu Indonesia dan merusak Demokrasi yg ber-as…"
  },
  {
    "id": "1519550344468271104",
    "lang": "in",
    "text": "RT @Sunwoobulol: @convomf Sayang. KAMI PUTRA DAN PUTRI INDONESIA, MENJUNJUNG BAHASA PERSATUAN! BAHASA INDONESIA!"
  },
  {
    "id": "1519550341842276352",
    "lang": "in",
    "text": "RT @27_dalbo: Perkumpulan Dokter Seluruh Indonesia (PDSI)\nResmi Dideklarasikan, Klaim Sudah Diakui Kemenkumham\nRabu (27/4/2022)\n\nKetum PDSI…"
  },
  {
    "id": "1519550337383731201",
    "lang": "in",
    "text": "RT @geloraco: Akun Ini Bongkar Alasan Tesla Tak Akan Investasi di Indonesia meski Sudah Cicipi Kopiko: Luhut Bohong!\nhttps://t.co/1WE7r1AODj"
  },
  {
    "id": "1519550319541293057",
    "lang": "in",
    "text": "filmbokep jepang # \nfree download sex indo # \nnonton vidieo bokep # \nvidio bokep lndo # \nvideo bokep barat vs jepang # \nbokep japan korea # \nbokep selingkuh hot # \njilbab bugil 2018 # \nvedio bokep # ...  #\nvidio poerno # #\nvidio bokep indonesia # #\nxxx p… https://t.co/WGw9KbpaC7"
  },
  {
    "id": "1519550318685868033",
    "lang": "in",
    "text": "RT @INABadminton: Babak 32 besar Kejuaraan Asia 2022 berlanjut besok. Berikut jadwal pemain-pemain Indonesia. Good luck!\n\n#BadmintonIndones…"
  },
  {
    "id": "1519550312201453569",
    "lang": "in",
    "text": "RT @meeayusri: @MALAYSIAVIRALL Real eh meninggal sbb jem 😭😭\n\nhttps://t.co/Uc0dYcjdox"
  },
  {
    "id": "1519550303011364865",
    "lang": "in",
    "text": "RT @MALAYSIAVIRALL: Jemm kat Indonesia sebab orang balik nak beraya kat kampung. Dulu  Pernah ada kes ada orang mati sebab 2 hari terkandas…"
  },
  {
    "id": "1519550299475611648",
    "lang": "in",
    "text": "RT @HopeOrangutan: 🥺🥺 EKSPLOITASI SATWA LIAR SIH INI. YUK BISA YUK NETIZEN INDONESIA LEBIH SELEKTIF DAN CERDAS LAGI BEDAIN TERKAIT INFLUENC…"
  },
  {
    "id": "1519550297726947328",
    "lang": "in",
    "text": "@JNECare barang yg seharusnya ke Bogor bisa kebuang jauh ke Indonesia bagian tengah, dan sampai sekarang pun pihak jne tidak tau  barangnya dimana? Gilaaaa parah benerrr"
  },
  {
    "id": "1519550289174401024",
    "lang": "in",
    "text": "RT @detikcom: Kedutaan Besar Amerika Serikat untuk Indonesia saat ini tengah membuka lowongan kerja berbagai macam posisi.  https://t.co/sn…"
  },
  {
    "id": "1519550282656813056",
    "lang": "in",
    "text": "RT @louveyuai: lemme introduce actress #LeeJieun aka #IU, upcoming k-movie yang bakal tayang di bulan juni nanti. Tenang film Broker ini ud…"
  },
  {
    "id": "1519550276747034624",
    "lang": "in",
    "text": "RT @jstcforemployee: cerita tentang salah satu perusahaan televisi yang dimiliki oleh konglomerat indonesia berlogo warna merah."
  },
  {
    "id": "1519550268907552774",
    "lang": "in",
    "text": "RT @HASapardan: Satu2nya partai di dunia\nYaitu Partai Demokrat\n\nAdanya di Indonesia.\n\nKetua Umum AHY anak SBY\nWakil Ketum Ibas adik AHY\n\nKe…"
  },
  {
    "id": "1519550268592992257",
    "lang": "in",
    "text": "Buktikan bahwa kita smua cinta damai.sampaikan aspirasi dengan santun.tertib dan tampa anarkis.agar indonesia tetap indah"
  },
  {
    "id": "1519550267351396352",
    "lang": "in",
    "text": "RT @mohmahfudmd: Sy jg tak prnh bilang TNI akan kudeta. Yg sy bilang, di Amerika Latin jika negara tak bs mengatasi perpecahan dan korupsi…"
  },
  {
    "id": "1519550265648889857",
    "lang": "in",
    "text": "@aripapndi Nahh knapa indonesia juga g ngasih sanksi? Pdhl kan menlunya mendukung kebebasan palestina? Wkwk"
  },
  {
    "id": "1519550258958987265",
    "lang": "in",
    "text": "RT @LurahIstana: penguasaan mayoritas perusahaan nanti akan dilakukan China(swastaisasi bumn contoh nya )Selanjutnya adalah pengerahan tena…"
  },
  {
    "id": "1519550254693056512",
    "lang": "in",
    "text": "RT @dianasayangku: Di twitter kita boleh flexing dengan kriteria gaji 2-3 digit. Tapi di dunia nyata, banyak pegawai toko, penjaga counter,…"
  },
  {
    "id": "1519550249424941056",
    "lang": "in",
    "text": "@hyang_wisnu @kemkominfo @PlateJohnny Pembangunan IKN diharapkan mampu mewujudkan pemerataan pembangunan di Indonesia.\n@kemkominfo @PlateJohnny"
  },
  {
    "id": "1519550237886455808",
    "lang": "in",
    "text": "RT @widarto63285827: YAMAN NEGARA KOMUNIS\n@MbahHerbal @Maya83206301\n@DumpalCandi17 @alextham878\n@abubakarsegaf @_MbakSri_\n@AyaniMel @Leonit…"
  },
  {
    "id": "1519550237832282112",
    "lang": "in",
    "text": "Orang ini salah kamar:\n1. Itu ucapan Bung Karno..Bu Mega mengutipnya\n2. Pernyataan itu u/ Muslim Indonesia (juga Hindu Indonesia &amp; Kristen Indonesia)\n3. Pernyataan itu u/ warga Indonesia, bukan u/ warga Arab\n4. Tetap aja @PDI_Perjuangan no 1 dlm survey (24%) https://t.co/Uwn4LJURBd"
  },
  {
    "id": "1519550226981605377",
    "lang": "in",
    "text": "RT @HopeOrangutan: 🥺🥺 EKSPLOITASI SATWA LIAR SIH INI. YUK BISA YUK NETIZEN INDONESIA LEBIH SELEKTIF DAN CERDAS LAGI BEDAIN TERKAIT INFLUENC…"
  },
  {
    "id": "1519550225240711169",
    "lang": "in",
    "text": "Ini Permintaan Serikat Petani Indonesia (SPI) Saat Harga TBS Kelapa Sawit Melemah|https://t.co/ksQhHGuymE.\n\nEditor: Handoyo . |  Reporter: Ratih Waseso"
  },
  {
    "id": "1519550219628998658",
    "lang": "in",
    "text": "RT @jstcforemployee: cerita tentang salah satu perusahaan televisi yang dimiliki oleh konglomerat indonesia berlogo warna merah."
  },
  {
    "id": "1519550211554611204",
    "lang": "in",
    "text": "RT @korantempo: Partai Mahasiswa resmi tercatat di Kementerian Hukum dan HAM. Proses pembentukan Partai Mahasiswa Indonesia yang cepat dipe…"
  },
  {
    "id": "1519550210254417921",
    "lang": "in",
    "text": "bismillah 9 wakil dari tim badminton indonesia masuk ke QF di badminton asia championship"
  },
  {
    "id": "1519550206198841344",
    "lang": "in",
    "text": "RT @EOJINcun: Tebak Lagu b aja\nTema: Indonesia Jadoel Gabrut\n13.00 https://t.co/n4Lsu0Uluo"
  },
  {
    "id": "1519550206102355968",
    "lang": "in",
    "text": "RT @PosIndonesia: #SahabatPos, Pos Indonesia kembali meraih penghargaan. Kali ini Pos Indonesia meraih Top Digital PR Award kategori BUMN.…"
  },
  {
    "id": "1519550194874204161",
    "lang": "in",
    "text": "RT @LuqmanBeeNKRI: Mahalnya biaya dokter di Indonesia yang sulit dijangkau rakyat menengah bawah itu, menurut saya, selama ini tidak lepas…"
  },
  {
    "id": "1519550194379272192",
    "lang": "in",
    "text": "RT @akun_ke9: Gw cuma pengen kupas tipis mengenai berita ini melalui video &gt;&gt;\nSebuah telegram lama dari kedutaan untuk Central Intelligence…"
  },
  {
    "id": "1519550181892517888",
    "lang": "in",
    "text": "RT @Juragantajirrr: BANDUNG - Relawan Erick Thohir Sahabat Indonesia (ETOS) Jawa Barat menyatakan dukungannya terhadap Menteri Badan Usaha…"
  },
  {
    "id": "1519550179292360704",
    "lang": "in",
    "text": "Dan lagi, ada orang yang mendapat insight dari luar negeri atau hidup di luar negeri lalu merasa paling open minded. Bukan hal yang mengejutkan memang kalau orang Indonesia itu mudah kena brainwash 🤭. https://t.co/2q8eUpFN0V"
  },
  {
    "id": "1519550174825414657",
    "lang": "in",
    "text": "RT @VVinTaebear__: Selamat siyaaang! Berapa target stream CT kita hari ini? Mau dapet cepek apa nopek tjeng? &lt;(￣︶￣)&gt;\n\nCuss mainkan PLnya. Y…"
  },
  {
    "id": "1519550174116282369",
    "lang": "in",
    "text": "@Mersinli_irem Assalamualaikum.. happy fasting from indonesia.."
  },
  {
    "id": "1519550159180341248",
    "lang": "in",
    "text": "Mix musik juga butuh setup yang memadai. Yuk rakit di Technoca, biar sesuai budget dan kebutuhan ~\n\n👉Follow instagram @technoca_indonesia⁣⁣⁣⁣⁣⁣⁣⁣\n⁣⁣\n#technoca #technoca_indonesia #laptopbandung #technology #follow #tech #indonesia #laptop #bandung #techno #pengetahuan https://t.co/MbfZ3bBUOM"
  },
  {
    "id": "1519550156022026240",
    "lang": "in",
    "text": "RT @MALAYSIAVIRALL: Jemm kat Indonesia sebab orang balik nak beraya kat kampung. Dulu  Pernah ada kes ada orang mati sebab 2 hari terkandas…"
  },
  {
    "id": "1519550152683364353",
    "lang": "in",
    "text": "@JPFBASE Padahal udh bagus Indonesia banget ya 😅"
  },
  {
    "id": "1519550141971107840",
    "lang": "in",
    "text": "SOGO dan Alun-Alun Department Store Terus Perkuat Dukungan UMKM Indonesia\n\nhttps://t.co/DL7RyUVXaM\n#idulfitri2022 #Liburan #lebaran #Lebaran2022 #UMKM #1Syawal"
  },
  {
    "id": "1519550141610430464",
    "lang": "in",
    "text": "Silaturahim, menjenguk kampung halaman...\n\nFenomena mudik Indonesia dikenal hingga mancanegara...\n\nMacet 16 Km dari arah Ibu Kota.\n\nhttps://t.co/Co2cNHOenZ\n\nDudung cantik banget"
  },
  {
    "id": "1519550139936894977",
    "lang": "in",
    "text": "@evylagi Kalo dibandingkan atau disamakan dgn negara lain, kayanya kurang tepat sih menurut saya. Ini kan Indonesia, budaya juga berbeda, cuaca juga berbeda, agama juga berbeda, rakyatnya juga berbeda, apalagi?"
  },
  {
    "id": "1519550138746048512",
    "lang": "in",
    "text": "RT @Budiars35809512: Salam buat bapak/ibu semua.\nSiapa tau ada yg membutuhkan asesories seperti di foto ini sy bisa membuatkanya dan siap k…"
  },
  {
    "id": "1519550127056121857",
    "lang": "in",
    "text": "RT @HopeOrangutan: 🥺🥺 EKSPLOITASI SATWA LIAR SIH INI. YUK BISA YUK NETIZEN INDONESIA LEBIH SELEKTIF DAN CERDAS LAGI BEDAIN TERKAIT INFLUENC…"
  },
  {
    "id": "1519550114502627329",
    "lang": "in",
    "text": "RT @Said_saputra19: @catastrophobes Bilang kalo agama ngajarin intoleran padahal bangsa Indonesia adalah bangsa yg punya 5 keyakinan tapi t…"
  },
  {
    "id": "1519550106688978944",
    "lang": "in",
    "text": "RT @geloraco: Akun Ini Bongkar Alasan Tesla Tak Akan Investasi di Indonesia meski Sudah Cicipi Kopiko: Luhut Bohong!\nhttps://t.co/1WE7r1AODj"
  },
  {
    "id": "1519550101508681729",
    "lang": "in",
    "text": "2&gt; terkait status jabatan Kepala Urusan Keuangan dan Kepala Urusan Umum Balai Harta Peninggalan Medan sehubungan dengan berlakunya Peraturan Menteri Hukum dan HAM Republik Indonesia Nomor 7 Tahun 2021 tentang Organisasi dan Tata Kerja Balai Harta Peninggalan \n#BHPMedan https://t.co/ynZgoRh1xR"
  },
  {
    "id": "1519550101143830530",
    "lang": "in",
    "text": "RT @NasDem: Selamat Ulang Tahun kakak Ivanhoe Semen Ketua DPP Partai NasDem\n\nSemoga selalu diberikan kesehatan selalu, panjang umur, dan murah rezeki. Amin 🙏\n\nTetap semangat bergerak untuk mewujudkan Restorasi Indonesia 🇮🇩\n\n#UlangTahun  #KaderNasDem … https://t.co/HCwvhPANy6"
  },
  {
    "id": "1519550100422684673",
    "lang": "in",
    "text": "RT @ay4m7ago: @detikcom Sekelas dokter yg nota bene otaknya encer bisa berfikir, masih mau di susupi politik pecah belah, dan siap2 sebenta…"
  },
  {
    "id": "1519550098023526401",
    "lang": "in",
    "text": "RT @ChangeOrg_ID: @dabelchisburger @Petrichor83_ @piyopikavet Koalisi Perlindungan Hewan Indonesia juga sedih banget kak, bayi-bayi monyet…"
  },
  {
    "id": "1519550094684528640",
    "lang": "in",
    "text": "RT @HopeOrangutan: 🥺🥺 EKSPLOITASI SATWA LIAR SIH INI. YUK BISA YUK NETIZEN INDONESIA LEBIH SELEKTIF DAN CERDAS LAGI BEDAIN TERKAIT INFLUENC…"
  },
  {
    "id": "1519550092218630146",
    "lang": "in",
    "text": "RT @xathrya: &gt; sekolah di luar negeri dibayarin uang rakyat\n&gt; specialized in \"financial crime &amp; corporate governance\"\n&gt; pulang kerja di bpk…"
  },
  {
    "id": "1519550091841122304",
    "lang": "in",
    "text": "@literarybase Cocok aja sih nder tapi buatku hasil translate-nya kurang bisa dimengerti, aku lebih rekomendasiin untuk buku bahasa Indonesia itu dari buku-bukunya pijar psikologi, Loving the Wounded Soul sama Indonesian First Mental Health Aid Booklet"
  },
  {
    "id": "1519550082097762304",
    "lang": "in",
    "text": "5. Kakanwil Kemenkumham Sumsel Harun Sulianto: kemudian jg BerAKHLAK (Berorientasi Pelayanan, Akuntabel, Kompeten, Harmonis, Loyal, Adaptif, dan Kolaboratif) untuk mewujudkan Indonesia Maju. \n@Kemenkumham_RI\n@kumhamsumsel \n#KumhamPasti\n#KumhamSumsel"
  },
  {
    "id": "1519550080063533056",
    "lang": "in",
    "text": "RT @dianasayangku: Di twitter kita boleh flexing dengan kriteria gaji 2-3 digit. Tapi di dunia nyata, banyak pegawai toko, penjaga counter,…"
  },
  {
    "id": "1519550075630153728",
    "lang": "in",
    "text": "Petit Island mengisahkan Lily, petualang muda yang ingin mengikuti jejak kakeknya yang pergi bertualang dan menceritakan kisah-kisah seru petualangannya.\n\nhttps://t.co/2FzZ1DcyrM"
  },
  {
    "id": "1519550074103115776",
    "lang": "in",
    "text": "RT @agis_official: Kenali Dan Waspadai Tokoh-Tokoh Syi'ah Indonesia Ini, Dari Penyanyi Hingga Anggota MUI Pusat. https://t.co/xFfgQQ6icQ"
  },
  {
    "id": "1519550070294990848",
    "lang": "in",
    "text": "RT @chacafebryani: Indonesia Teen\nPosisi Paling Enak Goyang Diatas\nMemek Becek , Kontol Terasa Licin &amp; linu\nCrot Diluar Takut Hamil 💦💦💦\n\nYu…"
  },
  {
    "id": "1519550068923469824",
    "lang": "in",
    "text": "RT @ChusnulCh__: Dua berita memalukan yg sy baca hari ini.\nPertama, mudik gratis yg dilakukan Pemprov tapi pesertanya memakai baju Kampanye…"
  },
  {
    "id": "1519550057720074240",
    "lang": "in",
    "text": "@riksayuda @BERKARYA_NET Dia lupa Indonesia pernah punya Bob Sadino yg selalu celana pendekan &amp; sendal teplek.\n\nPartai gurem gk udah ditanggapin. Brisik doank tp masuk senayan aj gk mampu. Apalagi 2024 entar. Bukannya naikin elektabilitas sendiri tp malah sibuk ngebuzzer black campaign lawan. wkwkwkwkw"
  },
  {
    "id": "1519550056344752129",
    "lang": "in",
    "text": "RT @chacafebryani: Indonesia Teen\nHijab Merah\nPart 2 Last\nDiajak Main Kerumah Pacar Pas Sepi\nCrot Ditetet 💦💦💦💦\n\nYuk ramaikan dan sports tru…"
  },
  {
    "id": "1519550054410821633",
    "lang": "in",
    "text": "Baru saja mengirim foto @ Bontang, Kalimantan Timur, Indonesia https://t.co/OgQRoXiJw6"
  },
  {
    "id": "1519550052305612800",
    "lang": "in",
    "text": "RT @MALAYSIAVIRALL: Jemm kat Indonesia sebab orang balik nak beraya kat kampung. Dulu  Pernah ada kes ada orang mati sebab 2 hari terkandas…"
  },
  {
    "id": "1519550041555300353",
    "lang": "in",
    "text": "RT @Djantjik: Menteri BUMN @erickthohir mengatakan batas normal penerbangan di Indonesia adalah minimal 400 pergerakan pesawat per hari.\nDa…"
  },
  {
    "id": "1519550039559139328",
    "lang": "in",
    "text": "RT @chacafebryani: Indonesia Teen\nHijab Merah\nPart 1\nDiajak Main Kerumah Pacar Pas Sepi\nCrot Ditetet 💦💦💦💦\n\nYuk ramaikan dan sports trus pro…"
  },
  {
    "id": "1519550039299100672",
    "lang": "in",
    "text": "RT @detikcom: Organisasi baru 'pesaing' IDI resmi dideklarasikan. Anak buah mantan Menkes Terawan Agus Putranto jadi ketua Perkumpulan Dokt…"
  },
  {
    "id": "1519550037873033221",
    "lang": "in",
    "text": "RT @jstcforemployee: cerita tentang salah satu perusahaan televisi yang dimiliki oleh konglomerat indonesia berlogo warna merah."
  },
  {
    "id": "1519550013449244673",
    "lang": "in",
    "text": "RT @MALAYSIAVIRALL: Jemm kat Indonesia sebab orang balik nak beraya kat kampung. Dulu  Pernah ada kes ada orang mati sebab 2 hari terkandas…"
  },
  {
    "id": "1519550013117845504",
    "lang": "in",
    "text": "RT @MALAYSIAVIRALL: Jemm kat Indonesia sebab orang balik nak beraya kat kampung. Dulu  Pernah ada kes ada orang mati sebab 2 hari terkandas…"
  },
  {
    "id": "1519550012816035840",
    "lang": "in",
    "text": "Kedutaan Besar Amerika Serikat untuk Indonesia saat ini tengah membuka lowongan kerja berbagai macam posisi.  https://t.co/snumqIa4vb"
  },
  {
    "id": "1519550012078059520",
    "lang": "in",
    "text": "RT @wangyibee: Daripada koar2 belain influencer yang ono mending nontonin channelnya om chanee kalaweit, orang prancis yang peduli sama sat…"
  },
  {
    "id": "1519550008365776896",
    "lang": "in",
    "text": "RT @karman_mustamin: Buat adik2 mahasiswa yg bilang kesejahteraan tdk didapatkan di era Jokowi, selamat mudik ke kampung halaman lewat jala…"
  },
  {
    "id": "1519550005442654208",
    "lang": "in",
    "text": "RT @HopeOrangutan: 🥺🥺 EKSPLOITASI SATWA LIAR SIH INI. YUK BISA YUK NETIZEN INDONESIA LEBIH SELEKTIF DAN CERDAS LAGI BEDAIN TERKAIT INFLUENC…"
  },
  {
    "id": "1519550002057859072",
    "lang": "in",
    "text": "5. Kakanwil Kemenkumham Sumsel Harun Sulianto: kemudian jg BerAKHLAK (Berorientasi Pelayanan, Akuntabel, Kompeten, Harmonis, Loyal, Adaptif, dan Kolaboratif) untuk mewujudkan Indonesia Maju. \n@Kemenkumham_RI\n@PalembangLpka\n#LpkaPalembang"
  },
  {
    "id": "1519550002057543680",
    "lang": "in",
    "text": "RT @hyang_wisnu: Perkuat Kerja Sama,Menteri Johnny: Indonesia-Iran Akan Terbitkan Prangko Peringatan Hubungan Bilateral\n\nMenkominfo,Johnny…"
  },
  {
    "id": "1519550000187195393",
    "lang": "in",
    "text": "@gusti_james @RusEmbJakarta Yugoslavia, libya, yaman, palestina, iran, iraq mana lagi ya? Wkwk indonesia keknya pernah 2 kali kalo gslh wkwk"
  },
  {
    "id": "1519549989449768963",
    "lang": "in",
    "text": "@Dionbonjovi181 @DJNXeo Indonesia harus waspada, bisa saja (karena merasa sdh banyak simpatisannya (baca kadrun), lalu menggunakan cara spt di Mesir, melakukan pembunuhan pemimpin bangsa. Sdh seharusnya pihak pertahanan dan keamanan segera menghanguskan gerombolan IM HTI ini."
  },
  {
    "id": "1519549987994349569",
    "lang": "in",
    "text": "RT @chacafebryani: Indonesia\nPenganten Baru\nLakiny 2x Crot Didalem\nBiar Cepet Bunting\n\nYuk ramaikan dan sports trus produk lokal https://t.…"
  },
  {
    "id": "1519549987503632384",
    "lang": "in",
    "text": "@OposisiCerdas Rakyat nya saja di huni kadrun dan cebong.. mana berwibawa indonesia dimata elon"
  },
  {
    "id": "1519549986996113409",
    "lang": "in",
    "text": "RT @geloraco: Akun Ini Bongkar Alasan Tesla Tak Akan Investasi di Indonesia meski Sudah Cicipi Kopiko: Luhut Bohong!\nhttps://t.co/1WE7r1AODj"
  },
  {
    "id": "1519549980708864000",
    "lang": "in",
    "text": "RT @C4pr3sAb4d1: Dulu admin ini udah ada belum atau masih di awang awang sampai lupa sejarah, Presiden ketemu pengusaha yang hanya pake cel…"
  },
  {
    "id": "1519549973301719040",
    "lang": "in",
    "text": "Official_MNCTV Jasa TTI (Trending Topic Indonesia). Murah dan Terpercaya. Melayani secepat ninja. Minat? CP 0895335397998 #TTI"
  },
  {
    "id": "1519549972240551936",
    "lang": "in",
    "text": "RT @chacafebryani: Indonesia Teen\nMemek Pacar Becek Banget\nBikin Kontol linu\nCrot Didalem💦💦💦\n\nYuk ramaikan dan sports trus produk lokal htt…"
  },
  {
    "id": "1519549968335327232",
    "lang": "in",
    "text": "RT @Baba97Alie: Dukungan yang diberikan oleh Panitia Kerja (Panja) Komisi VI DPR dalam menyelamatkan PT Garuda Indonesia (Persero) Tbk menu…"
  },
  {
    "id": "1519549964631691264",
    "lang": "in",
    "text": "RT @kungtaw_: #seriusnanya adakah referensi literatur yg bisa menjelaskan transisi penggunaan kata/frasa Bahasa Indonesia yg dulu lazim dip…"
  },
  {
    "id": "1519549963386388480",
    "lang": "in",
    "text": "SEA Games 2021 - Timnas U-23 Indonesia Satu Suara Ingin Raih Emas https://t.co/nQJj39CVzI\n\n#BanggaSepakBolaKita"
  },
  {
    "id": "1519549962748850176",
    "lang": "in",
    "text": "RT @Kuncicoin_id: 2 musisi hebat Indonesia yang merilis NFTMusicnya di KunciCoinNFT\n\nDapatkan bidding NFT Ifan Seventeen dan David Albert m…"
  },
  {
    "id": "1519549959250804738",
    "lang": "in",
    "text": "RT @firzahusainInc: Presiden Indonesia ke 2024 🤭🤭😊 https://t.co/AeNkMlOBhl"
  },
  {
    "id": "1519549957761814528",
    "lang": "in",
    "text": "RT @HopeOrangutan: 🥺🥺 EKSPLOITASI SATWA LIAR SIH INI. YUK BISA YUK NETIZEN INDONESIA LEBIH SELEKTIF DAN CERDAS LAGI BEDAIN TERKAIT INFLUENC…"
  },
  {
    "id": "1519549957459816448",
    "lang": "in",
    "text": "RT @chacafebryani: Indonesia Melayu\nAbis Bukber Lanjut Kehotel\nPart 2 Last\nCweny Berisik Banget Kena Kontol\n\nYuk ramaikan dan sports trus p…"
  },
  {
    "id": "1519549956797120512",
    "lang": "in",
    "text": "@yusuf_dumdum Dulu CPO Indonesia ditolak sama Eropa. Sekarang CPO dilarang ekspor banyak negara yg mencak mencak karena ketergantungan CPO dari luar negeri. Ini akan menjadi berkah bagi negara² penghasil CPO dunia sprti Malaysia, Thailand, Kolombia serta Nigeria."
  },
  {
    "id": "1519549955798491136",
    "lang": "in",
    "text": "RT @lelasukmagmail1: @IstanaLurah Kemarin mandalika gada yaa tinjauan utk teroras teroris. \nGilaa bener yaa ada para pejabat negara yg bisa…"
  },
  {
    "id": "1519549954599317504",
    "lang": "in",
    "text": "RT @bayuarisandee: Lagi di tahap The Daddies kalau menang bersyukur kalau kalah juga gak apa-apa, bukan gak mau support tapi udah banyak ba…"
  },
  {
    "id": "1519549952334376961",
    "lang": "in",
    "text": "SEA Games 2021 - Timnas U-23 Indonesia Satu Suara Ingin Raih Emas https://t.co/uwbraOrsV3\n\n#BanggaSepakBolaKita"
  },
  {
    "id": "1519549947863273472",
    "lang": "in",
    "text": "RT @HopeOrangutan: 🥺🥺 EKSPLOITASI SATWA LIAR SIH INI. YUK BISA YUK NETIZEN INDONESIA LEBIH SELEKTIF DAN CERDAS LAGI BEDAIN TERKAIT INFLUENC…"
  },
  {
    "id": "1519549939566903297",
    "lang": "in",
    "text": "RT @chacafebryani: Indonesia Melayu\nAbis Bukber Lanjut Kehotel\nPart 1\nCweny Berisik Banget Kena Kontol\n\nYuk ramaikan dan sports trus produk…"
  },
  {
    "id": "1519549938450935809",
    "lang": "in",
    "text": "RT @HopeOrangutan: 🥺🥺 EKSPLOITASI SATWA LIAR SIH INI. YUK BISA YUK NETIZEN INDONESIA LEBIH SELEKTIF DAN CERDAS LAGI BEDAIN TERKAIT INFLUENC…"
  },
  {
    "id": "1519549933673914374",
    "lang": "in",
    "text": "RT @BakarSmith: ...di Inggris. “Saat ini, NUCare-Lazisnu dipercaya untuk menyalurkan zakat fitrah, zakat maal, zakat profesi, infaq, sedeka…"
  },
  {
    "id": "1519549925519880192",
    "lang": "in",
    "text": "Gini amat hidup di Indonesia https://t.co/rxfK1eMhCl"
  },
  {
    "id": "1519549907480514560",
    "lang": "in",
    "text": "RT @chacafebryani: Indonesia Milf\nSkandal Jakarta\nPart 4 Last\nPerselingkuhan Pelakor\nHot Best Indonesia\n\nYuk ramaikan dan sports trus produ…"
  },
  {
    "id": "1519549905924399106",
    "lang": "in",
    "text": "RT @aksikitaindo: VIRAL!\n\nHewan liar dijadikan konten? Setujukah kamu?\n.\n.\n.\nSource: Boedi Setiawan - Universitas Airlangga, BBC\n#aksikitai…"
  },
  {
    "id": "1519549902992207872",
    "lang": "in",
    "text": "@bintangku206 @aniesbaswedan Kita doain aja supaya @aniesbaswedan menjadi presiden yang ke 2024 mas...\n\nKarena kita percaya bahwa Indonesia akan selalu dilindungi oleh Allah SWT ..."
  },
  {
    "id": "1519549900563881984",
    "lang": "in",
    "text": "Holding dengan nama Defend ID ini terdiri dari PT Len Industri (Persero) selaku induk holding, PT Dirgantara Indonesia, PT PAL Indonesia, PT Pindad, dan PT Dahana. Induk usaha, Defend Id ini langsung meneken kontrak kerja sama dengan Kementerian Pertahanan dan Kementerian BUMN."
  },
  {
    "id": "1519549896386174976",
    "lang": "in",
    "text": "Dubes Iran berharap agar Indonesia mampu membuat exhibition agar nantinya kedua negara bisa bersama-sama menerbitkan join stamp untuk memperingati 70 tahun hubungan bilateral https://t.co/rhVAS229o4"
  },
  {
    "id": "1519549894771757056",
    "lang": "in",
    "text": "RT @chacafebryani: Indonesia Milf\nSkandal Jakarta\nPart 3\nPerselingkuhan Pelakor\nHot Best Indonesia\n\nYuk ramaikan dan sports trus produk lok…"
  },
  {
    "id": "1519549893894762496",
    "lang": "in",
    "text": "RT @Juragantajirrr: Dari seluruh kalangan masyarakat Indonesia, terus memberikan dukungan kepada beliau menteri BUMN @erickthohir \n#ErickTh…"
  },
  {
    "id": "1519549891810578432",
    "lang": "in",
    "text": "RT @KompasTV: Jokowi Undang Presiden Ukraina Volodymyr Zelensky ke KTT G20 di Indonesia https://t.co/rXUvCGOEnk https://t.co/A0kkO79pKE"
  },
  {
    "id": "1519549890946564097",
    "lang": "in",
    "text": "RT @HopeOrangutan: 🥺🥺 EKSPLOITASI SATWA LIAR SIH INI. YUK BISA YUK NETIZEN INDONESIA LEBIH SELEKTIF DAN CERDAS LAGI BEDAIN TERKAIT INFLUENC…"
  },
  {
    "id": "1519549887829864449",
    "lang": "in",
    "text": "RT @jognli: Zhongli orang Indonesia"
  },
  {
    "id": "1519549887406256128",
    "lang": "in",
    "text": "@starfess Rate dari gw itu...\nJumlahin semua penduduk indonesia/10"
  },
  {
    "id": "1519549882679558149",
    "lang": "in",
    "text": "Bahan Perusak Ozone (BPO) dan melarang impor produk yang memakai Freon R22. Pihak dealer dan toko masih bisa menjual produk mereka sampai stock habis, dan melayani purna jual sampai dengan tahun 2030, saat dimana Freon R22 akan dihapus dari Indonesia."
  }
]